hw2/src/mult3detect.v

// mult3detect.v

module mult3detect
#(parameter DATA_WIDTH = 32)
    (
        input wire i_clk,
        input wire i_rst,
        input wire i_din,
        output reg o_dout
    );

    parameter S0 = 2'b00,
        S1 = 2'b01,
        S2 = 2'b10;

    reg [3:0] state = S0;
    reg [3:0] next_state;

    // STATE REGISTER
    always @(posedge i_clk) begin
        state <= 2'bxx;
        if (i_rst)  state <= S0;
        else        state <= next_state;
    end

    // OUT LOGIC
    always @(posedge i_clk) begin
        o_dout <= 1'bx;
        if (i_rst) o_dout <= 1'b1;
        else begin
            case (state)
                S0 : o_dout <= 1'b1;
                S1 : o_dout <= 1'b0;
                S2 : o_dout <= 1'b0;
                default : o_dout <= 1'bx;
            endcase
        end
    end

    // STATE MACHINE
    always @(state or i_din) begin
        next_state <= 2'bxx;
        case (state) 
            S0 :    if (i_din)  next_state <= S1;
                    else        next_state <= S0;
            S1 :    if (i_din)  next_state <= S2;
                    else        next_state <= S1;
            S2 :    if (i_din)  next_state <= S0;
                    else        next_state <= S2;
            default : next_state <= 2'bxx;
        endcase
    end


endmodule

hw2/verif/tb_mult3detect.sv

// tb_mult3detect.sv
//
// https://www.asic-world.com/systemverilog/system_task_function4.html

module tb_mult3detect;

    // testbench signals
    localparam DATA_WIDTH = 32;
    int num_errors;
    reg [DATA_WIDTH-1:0] tb_word;
    reg tb_exp; // expected output value of tb_dout
    reg tb_err;
    reg tb_clk;
    reg tb_rst;
    reg tb_din;
    wire tb_dout;

    // dut instantiation
    mult3detect #(.DATA_WIDTH(DATA_WIDTH)) dut (
        .i_clk(tb_clk),
        .i_rst(tb_rst),
        .i_din(tb_din),
        .o_dout(tb_dout)
    );

    task assert_and_report(input expected, input actual);
    begin
        if (actual == expected) begin
            $display("SUCCESS! Expected: %h, Actual: %h", expected, actual);
            tb_err = 1'b0;
        end else begin
            $display("FAILURE! Expected: %h, Actual: %h", expected, actual);
            num_errors = num_errors + 1;
            tb_err = 1'bx;
        end
    end
    endtask // assert_and_report

    int ones_count;
    task test_word(input [DATA_WIDTH-1:0] word);
    begin
        for (int i = 0; i < DATA_WIDTH; i++) begin
            if (word[i] == 1) begin
                ones_count++;
            end
        end
        $display("Ones count: %d", ones_count);
        if (ones_count % 3 == 0)    begin tb_exp = 1; end
        else                        begin tb_exp = 0; end
        // serialize word, LSB first in
        for (int i = 0; i < DATA_WIDTH; i++) begin
            tb_din = word[i];
            #10;
        end
        #20; // wait 2 clock cycles for output because dut uses 3-always-block model
        assert_and_report(tb_exp, tb_dout);
        ones_count = 0;
        tb_din = 0;
        tb_rst = 1; // reset the dut
        #20; // 2 clock cycles
        tb_rst = 0;
    end
    endtask // test_word

    always #5 tb_clk = ~tb_clk; // 100MHz clock
    int count = 0;

    initial begin
        $display("Beginning simulation...");
        $dumpfile("waveform.vcd");
        $dumpvars;

        num_errors = 0;
        tb_clk = 1;
        tb_rst = 1;
        tb_exp = 1'bx;

        #20; // buffer first 2 clock cycles to flush X's

        repeat (100) begin
            tb_rst = 0;
            tb_word = $urandom();
            $display("Word: %h = %b", tb_word, tb_word);
            test_word(tb_word);
            $display();
        end

        $display();
        $display("Total number of errors: %d", num_errors);
        $display();

        $finish;
    end // initial
endmodule

hw2/sim/waveform.vcd
$date
   Thu Oct 17 19:41:22 2024
$end

$version
  2023.2.2
  $dumpfile ("waveform.vcd") 
$end

$timescale
  1ps
$end

$scope module tb_mult3detect $end
$var reg 32 ! num_errors [31:0] $end
$var reg 32 " tb_word [31:0] $end
$var reg 1 # tb_exp $end
$var reg 1 $ tb_err $end
$var reg 1 % tb_clk $end
$var reg 1 & tb_rst $end
$var reg 1 ' tb_din $end
$var wire 1 ( tb_dout $end
$var reg 32 ) ones_count [31:0] $end
$var reg 32 * count [31:0] $end
$scope module dut $end
$var wire 1 + i_clk $end
$var wire 1 , i_rst $end
$var wire 1 - i_din $end
$var reg 1 . o_dout $end
$var reg 4 / state [3:0] $end
$var reg 4 0 next_state [3:0] $end
$upscope $end
$scope task assert_and_report $end
$var reg 1 1 expected $end
$var reg 1 2 actual $end
$upscope $end
$scope task test_word $end
$var reg 32 3 word [31:0] $end
$scope begin Block43_4 $end
$var reg 32 4 i [31:0] $end
$upscope $end
$scope begin Block52_5 $end
$var reg 32 5 i [31:0] $end
$upscope $end
$upscope $end
$upscope $end
$enddefinitions $end

#0
$dumpvars
b0 !
bx "
x#
x$
1%
1&
x'
1(
b0 )
b0 *
1+
1,
x-
1.
b0 /
b0 0
x1
x2
bx 3
b0 4
b0 5
$end

#5000
0%
0+

#10000
1%
1+
1.
b0 /
b0 0

#15000
0%
0+

#20000
b10000110100001000000011000000100 "
0#
1%
0&
0'
b1000 )
1+
0,
0-
1.
b0 /
b0 0
b10000110100001000000011000000100 3
b100000 4

#25000
0%
0+

#30000
1%
1+
1.
b0 /
b0 0
b1 5

#35000
0%
0+

#40000
1%
1'
1+
1-
1.
b0 /
b1 0
b10 5

#45000
0%
0+

#50000
1%
0'
1+
0-
1.
b1 /
b1 0
b11 5

#55000
0%
0+

#60000
1%
0(
1+
0.
b1 /
b1 0
b100 5

#65000
0%
0+

#70000
1%
1+
0.
b1 /
b1 0
b101 5

#75000
0%
0+

#80000
1%
1+
0.
b1 /
b1 0
b110 5

#85000
0%
0+

#90000
1%
1+
0.
b1 /
b1 0
b111 5

#95000
0%
0+

#100000
1%
1+
0.
b1 /
b1 0
b1000 5

#105000
0%
0+

#110000
1%
1'
1+
1-
0.
b1 /
b10 0
b1001 5

#115000
0%
0+

#120000
1%
1+
0.
b10 /
b0 0
b1010 5

#125000
0%
0+

#130000
1%
0'
1+
0-
0.
b0 /
b0 0
b1011 5

#135000
0%
0+

#140000
1%
1(
1+
1.
b0 /
b0 0
b1100 5

#145000
0%
0+

#150000
1%
1+
1.
b0 /
b0 0
b1101 5

#155000
0%
0+

#160000
1%
1+
1.
b0 /
b0 0
b1110 5

#165000
0%
0+

#170000
1%
1+
1.
b0 /
b0 0
b1111 5

#175000
0%
0+

#180000
1%
1+
1.
b0 /
b0 0
b10000 5

#185000
0%
0+

#190000
1%
1+
1.
b0 /
b0 0
b10001 5

#195000
0%
0+

#200000
1%
1'
1+
1-
1.
b0 /
b1 0
b10010 5

#205000
0%
0+

#210000
1%
0'
1+
0-
1.
b1 /
b1 0
b10011 5

#215000
0%
0+

#220000
1%
0(
1+
0.
b1 /
b1 0
b10100 5

#225000
0%
0+

#230000
1%
1+
0.
b1 /
b1 0
b10101 5

#235000
0%
0+

#240000
1%
1+
0.
b1 /
b1 0
b10110 5

#245000
0%
0+

#250000
1%
1'
1+
1-
0.
b1 /
b10 0
b10111 5

#255000
0%
0+

#260000
1%
0'
1+
0-
0.
b10 /
b10 0
b11000 5

#265000
0%
0+

#270000
1%
1'
1+
1-
0.
b10 /
b0 0
b11001 5

#275000
0%
0+

#280000
1%
1+
0.
b0 /
b1 0
b11010 5

#285000
0%
0+

#290000
1%
0'
1(
1+
0-
1.
b1 /
b1 0
b11011 5

#295000
0%
0+

#300000
1%
0(
1+
0.
b1 /
b1 0
b11100 5

#305000
0%
0+

#310000
1%
1+
0.
b1 /
b1 0
b11101 5

#315000
0%
0+

#320000
1%
1+
0.
b1 /
b1 0
b11110 5

#325000
0%
0+

#330000
1%
1'
1+
1-
0.
b1 /
b10 0
b11111 5

#335000
0%
0+

#340000
1%
1+
0.
b10 /
b0 0
b100000 5

#345000
0%
0+

#350000
1%
1+
0.
b0 /
b1 0

#355000
0%
0+

#360000
0$
1%
1&
0'
1(
b0 )
1+
1,
0-
1.
b0 /
b0 0
01
02

#365000
0%
0+

#370000
1%
1+
1.
b0 /
b0 0

#375000
0%
0+

#380000
b1110001111111101100111001111010 "
1#
1%
0&
b10101 )
1+
0,
1.
b0 /
b0 0
b1110001111111101100111001111010 3
b100000 4
b0 5

#385000
0%
0+

#390000
1%
1'
1+
1-
1.
b0 /
b1 0
b1 5

#395000
0%
0+

#400000
1%
0'
1+
0-
1.
b1 /
b1 0
b10 5

#405000
0%
0+

#410000
1%
1'
0(
1+
1-
0.
b1 /
b10 0
b11 5

#415000
0%
0+

#420000
1%
1+
0.
b10 /
b0 0
b100 5

#425000
0%
0+

#430000
1%
1+
0.
b0 /
b1 0
b101 5

#435000
0%
0+

#440000
1%
1(
1+
1.
b1 /
b10 0
b110 5

#445000
0%
0+

#450000
1%
0'
0(
1+
0-
0.
b10 /
b10 0
b111 5

#455000
0%
0+

#460000
1%
1+
0.
b10 /
b10 0
b1000 5

#465000
0%
0+

#470000
1%
1'
1+
1-
0.
b10 /
b0 0
b1001 5

#475000
0%
0+

#480000
1%
1+
0.
b0 /
b1 0
b1010 5

#485000
0%
0+

#490000
1%
1(
1+
1.
b1 /
b10 0
b1011 5

#495000
0%
0+

#500000
1%
0'
0(
1+
0-
0.
b10 /
b10 0
b1100 5

#505000
0%
0+

#510000
1%
1+
0.
b10 /
b10 0
b1101 5

#515000
0%
0+

#520000
1%
1'
1+
1-
0.
b10 /
b0 0
b1110 5

#525000
0%
0+

#530000
1%
1+
0.
b0 /
b1 0
b1111 5

#535000
0%
0+

#540000
1%
0'
1(
1+
0-
1.
b1 /
b1 0
b10000 5

#545000
0%
0+

#550000
1%
1'
0(
1+
1-
0.
b1 /
b10 0
b10001 5

#555000
0%
0+

#560000
1%
1+
0.
b10 /
b0 0
b10010 5

#565000
0%
0+

#570000
1%
1+
0.
b0 /
b1 0
b10011 5

#575000
0%
0+

#580000
1%
1(
1+
1.
b1 /
b10 0
b10100 5

#585000
0%
0+

#590000
1%
0(
1+
0.
b10 /
b0 0
b10101 5

#595000
0%
0+

#600000
1%
1+
0.
b0 /
b1 0
b10110 5

#605000
0%
0+

#610000
1%
1(
1+
1.
b1 /
b10 0
b10111 5

#615000
0%
0+

#620000
1%
0(
1+
0.
b10 /
b0 0
b11000 5

#625000
0%
0+

#630000
1%
0'
1+
0-
0.
b0 /
b0 0
b11001 5

#635000
0%
0+

#640000
1%
1(
1+
1.
b0 /
b0 0
b11010 5

#645000
0%
0+

#650000
1%
1+
1.
b0 /
b0 0
b11011 5

#655000
0%
0+

#660000
1%
1'
1+
1-
1.
b0 /
b1 0
b11100 5

#665000
0%
0+

#670000
1%
1+
1.
b1 /
b10 0
b11101 5

#675000
0%
0+

#680000
1%
0(
1+
0.
b10 /
b0 0
b11110 5

#685000
0%
0+

#690000
1%
0'
1+
0-
0.
b0 /
b0 0
b11111 5

#695000
0%
0+

#700000
1%
1(
1+
1.
b0 /
b0 0
b100000 5

#705000
0%
0+

#710000
1%
1+
1.
b0 /
b0 0

#715000
0%
0+

#720000
1%
1&
b0 )
1+
1,
1.
b0 /
b0 0
11
12

#725000
0%
0+

#730000
1%
1+
1.
b0 /
b0 0

#735000
0%
0+

#740000
b1100010010111100011000100000010 "
1%
0&
b1100 )
1+
0,
1.
b0 /
b0 0
b1100010010111100011000100000010 3
b100000 4
b0 5

#745000
0%
0+

#750000
1%
1'
1+
1-
1.
b0 /
b1 0
b1 5

#755000
0%
0+

#760000
1%
0'
1+
0-
1.
b1 /
b1 0
b10 5

#765000
0%
0+

#770000
1%
0(
1+
0.
b1 /
b1 0
b11 5

#775000
0%
0+

#780000
1%
1+
0.
b1 /
b1 0
b100 5

#785000
0%
0+

#790000
1%
1+
0.
b1 /
b1 0
b101 5

#795000
0%
0+

#800000
1%
1+
0.
b1 /
b1 0
b110 5

#805000
0%
0+

#810000
1%
1+
0.
b1 /
b1 0
b111 5

#815000
0%
0+

#820000
1%
1'
1+
1-
0.
b1 /
b10 0
b1000 5

#825000
0%
0+

#830000
1%
0'
1+
0-
0.
b10 /
b10 0
b1001 5

#835000
0%
0+

#840000
1%
1+
0.
b10 /
b10 0
b1010 5

#845000
0%
0+

#850000
1%
1+
0.
b10 /
b10 0
b1011 5

#855000
0%
0+

#860000
1%
1'
1+
1-
0.
b10 /
b0 0
b1100 5

#865000
0%
0+

#870000
1%
1+
0.
b0 /
b1 0
b1101 5

#875000
0%
0+

#880000
1%
0'
1(
1+
0-
1.
b1 /
b1 0
b1110 5

#885000
0%
0+

#890000
1%
0(
1+
0.
b1 /
b1 0
b1111 5

#895000
0%
0+

#900000
1%
1+
0.
b1 /
b1 0
b10000 5

#905000
0%
0+

#910000
1%
1'
1+
1-
0.
b1 /
b10 0
b10001 5

#915000
0%
0+

#920000
1%
1+
0.
b10 /
b0 0
b10010 5

#925000
0%
0+

#930000
1%
1+
0.
b0 /
b1 0
b10011 5

#935000
0%
0+

#940000
1%
1(
1+
1.
b1 /
b10 0
b10100 5

#945000
0%
0+

#950000
1%
0'
0(
1+
0-
0.
b10 /
b10 0
b10101 5

#955000
0%
0+

#960000
1%
1'
1+
1-
0.
b10 /
b0 0
b10110 5

#965000
0%
0+

#970000
1%
0'
1+
0-
0.
b0 /
b0 0
b10111 5

#975000
0%
0+

#980000
1%
1(
1+
1.
b0 /
b0 0
b11000 5

#985000
0%
0+

#990000
1%
1'
1+
1-
1.
b0 /
b1 0
b11001 5

#995000
0%
0+

#1000000
1%
0'
1+
0-
1.
b1 /
b1 0
b11010 5

#1005000
0%
0+

#1010000
1%
0(
1+
0.
b1 /
b1 0
b11011 5

#1015000
0%
0+

#1020000
1%
1+
0.
b1 /
b1 0
b11100 5

#1025000
0%
0+

#1030000
1%
1'
1+
1-
0.
b1 /
b10 0
b11101 5

#1035000
0%
0+

#1040000
1%
1+
0.
b10 /
b0 0
b11110 5

#1045000
0%
0+

#1050000
1%
0'
1+
0-
0.
b0 /
b0 0
b11111 5

#1055000
0%
0+

#1060000
1%
1(
1+
1.
b0 /
b0 0
b100000 5

#1065000
0%
0+

#1070000
1%
1+
1.
b0 /
b0 0

#1075000
0%
0+

#1080000
1%
1&
b0 )
1+
1,
1.
b0 /
b0 0

#1085000
0%
0+

#1090000
1%
1+
1.
b0 /
b0 0

#1095000
0%
0+

#1100000
b1110111001101011011001011001001 "
1%
0&
1'
b10010 )
1+
0,
1-
1.
b0 /
b1 0
b1110111001101011011001011001001 3
b100000 4
b0 5

#1105000
0%
0+

#1110000
1%
0'
1+
0-
1.
b1 /
b1 0
b1 5

#1115000
0%
0+

#1120000
1%
0(
1+
0.
b1 /
b1 0
b10 5

#1125000
0%
0+

#1130000
1%
1'
1+
1-
0.
b1 /
b10 0
b11 5

#1135000
0%
0+

#1140000
1%
0'
1+
0-
0.
b10 /
b10 0
b100 5

#1145000
0%
0+

#1150000
1%
1+
0.
b10 /
b10 0
b101 5

#1155000
0%
0+

#1160000
1%
1'
1+
1-
0.
b10 /
b0 0
b110 5

#1165000
0%
0+

#1170000
1%
1+
0.
b0 /
b1 0
b111 5

#1175000
0%
0+

#1180000
1%
0'
1(
1+
0-
1.
b1 /
b1 0
b1000 5

#1185000
0%
0+

#1190000
1%
1'
0(
1+
1-
0.
b1 /
b10 0
b1001 5

#1195000
0%
0+

#1200000
1%
0'
1+
0-
0.
b10 /
b10 0
b1010 5

#1205000
0%
0+

#1210000
1%
1+
0.
b10 /
b10 0
b1011 5

#1215000
0%
0+

#1220000
1%
1'
1+
1-
0.
b10 /
b0 0
b1100 5

#1225000
0%
0+

#1230000
1%
1+
0.
b0 /
b1 0
b1101 5

#1235000
0%
0+

#1240000
1%
0'
1(
1+
0-
1.
b1 /
b1 0
b1110 5

#1245000
0%
0+

#1250000
1%
1'
0(
1+
1-
0.
b1 /
b10 0
b1111 5

#1255000
0%
0+

#1260000
1%
1+
0.
b10 /
b0 0
b10000 5

#1265000
0%
0+

#1270000
1%
0'
1+
0-
0.
b0 /
b0 0
b10001 5

#1275000
0%
0+

#1280000
1%
1'
1(
1+
1-
1.
b0 /
b1 0
b10010 5

#1285000
0%
0+

#1290000
1%
0'
1+
0-
1.
b1 /
b1 0
b10011 5

#1295000
0%
0+

#1300000
1%
1'
0(
1+
1-
0.
b1 /
b10 0
b10100 5

#1305000
0%
0+

#1310000
1%
1+
0.
b10 /
b0 0
b10101 5

#1315000
0%
0+

#1320000
1%
0'
1+
0-
0.
b0 /
b0 0
b10110 5

#1325000
0%
0+

#1330000
1%
1(
1+
1.
b0 /
b0 0
b10111 5

#1335000
0%
0+

#1340000
1%
1'
1+
1-
1.
b0 /
b1 0
b11000 5

#1345000
0%
0+

#1350000
1%
1+
1.
b1 /
b10 0
b11001 5

#1355000
0%
0+

#1360000
1%
0(
1+
0.
b10 /
b0 0
b11010 5

#1365000
0%
0+

#1370000
1%
0'
1+
0-
0.
b0 /
b0 0
b11011 5

#1375000
0%
0+

#1380000
1%
1'
1(
1+
1-
1.
b0 /
b1 0
b11100 5

#1385000
0%
0+

#1390000
1%
1+
1.
b1 /
b10 0
b11101 5

#1395000
0%
0+

#1400000
1%
0(
1+
0.
b10 /
b0 0
b11110 5

#1405000
0%
0+

#1410000
1%
0'
1+
0-
0.
b0 /
b0 0
b11111 5

#1415000
0%
0+

#1420000
1%
1(
1+
1.
b0 /
b0 0
b100000 5

#1425000
0%
0+

#1430000
1%
1+
1.
b0 /
b0 0

#1435000
0%
0+

#1440000
1%
1&
b0 )
1+
1,
1.
b0 /
b0 0

#1445000
0%
0+

#1450000
1%
1+
1.
b0 /
b0 0

#1455000
0%
0+

#1460000
b1111101010001101001101000000110 "
1%
0&
b1111 )
1+
0,
1.
b0 /
b0 0
b1111101010001101001101000000110 3
b100000 4
b0 5

#1465000
0%
0+

#1470000
1%
1'
1+
1-
1.
b0 /
b1 0
b1 5

#1475000
0%
0+

#1480000
1%
1+
1.
b1 /
b10 0
b10 5

#1485000
0%
0+

#1490000
1%
0'
0(
1+
0-
0.
b10 /
b10 0
b11 5

#1495000
0%
0+

#1500000
1%
1+
0.
b10 /
b10 0
b100 5

#1505000
0%
0+

#1510000
1%
1+
0.
b10 /
b10 0
b101 5

#1515000
0%
0+

#1520000
1%
1+
0.
b10 /
b10 0
b110 5

#1525000
0%
0+

#1530000
1%
1+
0.
b10 /
b10 0
b111 5

#1535000
0%
0+

#1540000
1%
1+
0.
b10 /
b10 0
b1000 5

#1545000
0%
0+

#1550000
1%
1'
1+
1-
0.
b10 /
b0 0
b1001 5

#1555000
0%
0+

#1560000
1%
0'
1+
0-
0.
b0 /
b0 0
b1010 5

#1565000
0%
0+

#1570000
1%
1'
1(
1+
1-
1.
b0 /
b1 0
b1011 5

#1575000
0%
0+

#1580000
1%
1+
1.
b1 /
b10 0
b1100 5

#1585000
0%
0+

#1590000
1%
0'
0(
1+
0-
0.
b10 /
b10 0
b1101 5

#1595000
0%
0+

#1600000
1%
1+
0.
b10 /
b10 0
b1110 5

#1605000
0%
0+

#1610000
1%
1'
1+
1-
0.
b10 /
b0 0
b1111 5

#1615000
0%
0+

#1620000
1%
0'
1+
0-
0.
b0 /
b0 0
b10000 5

#1625000
0%
0+

#1630000
1%
1'
1(
1+
1-
1.
b0 /
b1 0
b10001 5

#1635000
0%
0+

#1640000
1%
1+
1.
b1 /
b10 0
b10010 5

#1645000
0%
0+

#1650000
1%
0'
0(
1+
0-
0.
b10 /
b10 0
b10011 5

#1655000
0%
0+

#1660000
1%
1+
0.
b10 /
b10 0
b10100 5

#1665000
0%
0+

#1670000
1%
1+
0.
b10 /
b10 0
b10101 5

#1675000
0%
0+

#1680000
1%
1'
1+
1-
0.
b10 /
b0 0
b10110 5

#1685000
0%
0+

#1690000
1%
0'
1+
0-
0.
b0 /
b0 0
b10111 5

#1695000
0%
0+

#1700000
1%
1'
1(
1+
1-
1.
b0 /
b1 0
b11000 5

#1705000
0%
0+

#1710000
1%
0'
1+
0-
1.
b1 /
b1 0
b11001 5

#1715000
0%
0+

#1720000
1%
1'
0(
1+
1-
0.
b1 /
b10 0
b11010 5

#1725000
0%
0+

#1730000
1%
1+
0.
b10 /
b0 0
b11011 5

#1735000
0%
0+

#1740000
1%
1+
0.
b0 /
b1 0
b11100 5

#1745000
0%
0+

#1750000
1%
1(
1+
1.
b1 /
b10 0
b11101 5

#1755000
0%
0+

#1760000
1%
0(
1+
0.
b10 /
b0 0
b11110 5

#1765000
0%
0+

#1770000
1%
0'
1+
0-
0.
b0 /
b0 0
b11111 5

#1775000
0%
0+

#1780000
1%
1(
1+
1.
b0 /
b0 0
b100000 5

#1785000
0%
0+

#1790000
1%
1+
1.
b0 /
b0 0

#1795000
0%
0+

#1800000
1%
1&
b0 )
1+
1,
1.
b0 /
b0 0

#1805000
0%
0+

#1810000
1%
1+
1.
b0 /
b0 0

#1815000
0%
0+

#1820000
b100111000001111111100101110011 "
1%
0&
1'
b10010 )
1+
0,
1-
1.
b0 /
b1 0
b100111000001111111100101110011 3
b100000 4
b0 5

#1825000
0%
0+

#1830000
1%
1+
1.
b1 /
b10 0
b1 5

#1835000
0%
0+

#1840000
1%
0'
0(
1+
0-
0.
b10 /
b10 0
b10 5

#1845000
0%
0+

#1850000
1%
1+
0.
b10 /
b10 0
b11 5

#1855000
0%
0+

#1860000
1%
1'
1+
1-
0.
b10 /
b0 0
b100 5

#1865000
0%
0+

#1870000
1%
1+
0.
b0 /
b1 0
b101 5

#1875000
0%
0+

#1880000
1%
1(
1+
1.
b1 /
b10 0
b110 5

#1885000
0%
0+

#1890000
1%
0'
0(
1+
0-
0.
b10 /
b10 0
b111 5

#1895000
0%
0+

#1900000
1%
1'
1+
1-
0.
b10 /
b0 0
b1000 5

#1905000
0%
0+

#1910000
1%
0'
1+
0-
0.
b0 /
b0 0
b1001 5

#1915000
0%
0+

#1920000
1%
1(
1+
1.
b0 /
b0 0
b1010 5

#1925000
0%
0+

#1930000
1%
1'
1+
1-
1.
b0 /
b1 0
b1011 5

#1935000
0%
0+

#1940000
1%
1+
1.
b1 /
b10 0
b1100 5

#1945000
0%
0+

#1950000
1%
0(
1+
0.
b10 /
b0 0
b1101 5

#1955000
0%
0+

#1960000
1%
1+
0.
b0 /
b1 0
b1110 5

#1965000
0%
0+

#1970000
1%
1(
1+
1.
b1 /
b10 0
b1111 5

#1975000
0%
0+

#1980000
1%
0(
1+
0.
b10 /
b0 0
b10000 5

#1985000
0%
0+

#1990000
1%
1+
0.
b0 /
b1 0
b10001 5

#1995000
0%
0+

#2000000
1%
1(
1+
1.
b1 /
b10 0
b10010 5

#2005000
0%
0+

#2010000
1%
0'
0(
1+
0-
0.
b10 /
b10 0
b10011 5

#2015000
0%
0+

#2020000
1%
1+
0.
b10 /
b10 0
b10100 5

#2025000
0%
0+

#2030000
1%
1+
0.
b10 /
b10 0
b10101 5

#2035000
0%
0+

#2040000
1%
1+
0.
b10 /
b10 0
b10110 5

#2045000
0%
0+

#2050000
1%
1+
0.
b10 /
b10 0
b10111 5

#2055000
0%
0+

#2060000
1%
1'
1+
1-
0.
b10 /
b0 0
b11000 5

#2065000
0%
0+

#2070000
1%
1+
0.
b0 /
b1 0
b11001 5

#2075000
0%
0+

#2080000
1%
1(
1+
1.
b1 /
b10 0
b11010 5

#2085000
0%
0+

#2090000
1%
0'
0(
1+
0-
0.
b10 /
b10 0
b11011 5

#2095000
0%
0+

#2100000
1%
1+
0.
b10 /
b10 0
b11100 5

#2105000
0%
0+

#2110000
1%
1'
1+
1-
0.
b10 /
b0 0
b11101 5

#2115000
0%
0+

#2120000
1%
0'
1+
0-
0.
b0 /
b0 0
b11110 5

#2125000
0%
0+

#2130000
1%
1(
1+
1.
b0 /
b0 0
b11111 5

#2135000
0%
0+

#2140000
1%
1+
1.
b0 /
b0 0
b100000 5

#2145000
0%
0+

#2150000
1%
1+
1.
b0 /
b0 0

#2155000
0%
0+

#2160000
1%
1&
b0 )
1+
1,
1.
b0 /
b0 0

#2165000
0%
0+

#2170000
1%
1+
1.
b0 /
b0 0

#2175000
0%
0+

#2180000
b101000001000111000100111110000 "
1%
0&
b1100 )
1+
0,
1.
b0 /
b0 0
b101000001000111000100111110000 3
b100000 4
b0 5

#2185000
0%
0+

#2190000
1%
1+
1.
b0 /
b0 0
b1 5

#2195000
0%
0+

#2200000
1%
1+
1.
b0 /
b0 0
b10 5

#2205000
0%
0+

#2210000
1%
1+
1.
b0 /
b0 0
b11 5

#2215000
0%
0+

#2220000
1%
1'
1+
1-
1.
b0 /
b1 0
b100 5

#2225000
0%
0+

#2230000
1%
1+
1.
b1 /
b10 0
b101 5

#2235000
0%
0+

#2240000
1%
0(
1+
0.
b10 /
b0 0
b110 5

#2245000
0%
0+

#2250000
1%
1+
0.
b0 /
b1 0
b111 5

#2255000
0%
0+

#2260000
1%
1(
1+
1.
b1 /
b10 0
b1000 5

#2265000
0%
0+

#2270000
1%
0'
0(
1+
0-
0.
b10 /
b10 0
b1001 5

#2275000
0%
0+

#2280000
1%
1+
0.
b10 /
b10 0
b1010 5

#2285000
0%
0+

#2290000
1%
1'
1+
1-
0.
b10 /
b0 0
b1011 5

#2295000
0%
0+

#2300000
1%
0'
1+
0-
0.
b0 /
b0 0
b1100 5

#2305000
0%
0+

#2310000
1%
1(
1+
1.
b0 /
b0 0
b1101 5

#2315000
0%
0+

#2320000
1%
1+
1.
b0 /
b0 0
b1110 5

#2325000
0%
0+

#2330000
1%
1'
1+
1-
1.
b0 /
b1 0
b1111 5

#2335000
0%
0+

#2340000
1%
1+
1.
b1 /
b10 0
b10000 5

#2345000
0%
0+

#2350000
1%
0(
1+
0.
b10 /
b0 0
b10001 5

#2355000
0%
0+

#2360000
1%
0'
1+
0-
0.
b0 /
b0 0
b10010 5

#2365000
0%
0+

#2370000
1%
1(
1+
1.
b0 /
b0 0
b10011 5

#2375000
0%
0+

#2380000
1%
1+
1.
b0 /
b0 0
b10100 5

#2385000
0%
0+

#2390000
1%
1'
1+
1-
1.
b0 /
b1 0
b10101 5

#2395000
0%
0+

#2400000
1%
0'
1+
0-
1.
b1 /
b1 0
b10110 5

#2405000
0%
0+

#2410000
1%
0(
1+
0.
b1 /
b1 0
b10111 5

#2415000
0%
0+

#2420000
1%
1+
0.
b1 /
b1 0
b11000 5

#2425000
0%
0+

#2430000
1%
1+
0.
b1 /
b1 0
b11001 5

#2435000
0%
0+

#2440000
1%
1+
0.
b1 /
b1 0
b11010 5

#2445000
0%
0+

#2450000
1%
1'
1+
1-
0.
b1 /
b10 0
b11011 5

#2455000
0%
0+

#2460000
1%
0'
1+
0-
0.
b10 /
b10 0
b11100 5

#2465000
0%
0+

#2470000
1%
1'
1+
1-
0.
b10 /
b0 0
b11101 5

#2475000
0%
0+

#2480000
1%
0'
1+
0-
0.
b0 /
b0 0
b11110 5

#2485000
0%
0+

#2490000
1%
1(
1+
1.
b0 /
b0 0
b11111 5

#2495000
0%
0+

#2500000
1%
1+
1.
b0 /
b0 0
b100000 5

#2505000
0%
0+

#2510000
1%
1+
1.
b0 /
b0 0

#2515000
0%
0+

#2520000
1%
1&
b0 )
1+
1,
1.
b0 /
b0 0

#2525000
0%
0+

#2530000
1%
1+
1.
b0 /
b0 0

#2535000
0%
0+

#2540000
b11110010101010000000001010 "
0#
1%
0&
b1010 )
1+
0,
1.
b0 /
b0 0
b11110010101010000000001010 3
b100000 4
b0 5

#2545000
0%
0+

#2550000
1%
1'
1+
1-
1.
b0 /
b1 0
b1 5

#2555000
0%
0+

#2560000
1%
0'
1+
0-
1.
b1 /
b1 0
b10 5

#2565000
0%
0+

#2570000
1%
1'
0(
1+
1-
0.
b1 /
b10 0
b11 5

#2575000
0%
0+

#2580000
1%
0'
1+
0-
0.
b10 /
b10 0
b100 5

#2585000
0%
0+

#2590000
1%
1+
0.
b10 /
b10 0
b101 5

#2595000
0%
0+

#2600000
1%
1+
0.
b10 /
b10 0
b110 5

#2605000
0%
0+

#2610000
1%
1+
0.
b10 /
b10 0
b111 5

#2615000
0%
0+

#2620000
1%
1+
0.
b10 /
b10 0
b1000 5

#2625000
0%
0+

#2630000
1%
1+
0.
b10 /
b10 0
b1001 5

#2635000
0%
0+

#2640000
1%
1+
0.
b10 /
b10 0
b1010 5

#2645000
0%
0+

#2650000
1%
1+
0.
b10 /
b10 0
b1011 5

#2655000
0%
0+

#2660000
1%
1+
0.
b10 /
b10 0
b1100 5

#2665000
0%
0+

#2670000
1%
1'
1+
1-
0.
b10 /
b0 0
b1101 5

#2675000
0%
0+

#2680000
1%
0'
1+
0-
0.
b0 /
b0 0
b1110 5

#2685000
0%
0+

#2690000
1%
1'
1(
1+
1-
1.
b0 /
b1 0
b1111 5

#2695000
0%
0+

#2700000
1%
0'
1+
0-
1.
b1 /
b1 0
b10000 5

#2705000
0%
0+

#2710000
1%
1'
0(
1+
1-
0.
b1 /
b10 0
b10001 5

#2715000
0%
0+

#2720000
1%
0'
1+
0-
0.
b10 /
b10 0
b10010 5

#2725000
0%
0+

#2730000
1%
1'
1+
1-
0.
b10 /
b0 0
b10011 5

#2735000
0%
0+

#2740000
1%
0'
1+
0-
0.
b0 /
b0 0
b10100 5

#2745000
0%
0+

#2750000
1%
1(
1+
1.
b0 /
b0 0
b10101 5

#2755000
0%
0+

#2760000
1%
1'
1+
1-
1.
b0 /
b1 0
b10110 5

#2765000
0%
0+

#2770000
1%
1+
1.
b1 /
b10 0
b10111 5

#2775000
0%
0+

#2780000
1%
0(
1+
0.
b10 /
b0 0
b11000 5

#2785000
0%
0+

#2790000
1%
1+
0.
b0 /
b1 0
b11001 5

#2795000
0%
0+

#2800000
1%
0'
1(
1+
0-
1.
b1 /
b1 0
b11010 5

#2805000
0%
0+

#2810000
1%
0(
1+
0.
b1 /
b1 0
b11011 5

#2815000
0%
0+

#2820000
1%
1+
0.
b1 /
b1 0
b11100 5

#2825000
0%
0+

#2830000
1%
1+
0.
b1 /
b1 0
b11101 5

#2835000
0%
0+

#2840000
1%
1+
0.
b1 /
b1 0
b11110 5

#2845000
0%
0+

#2850000
1%
1+
0.
b1 /
b1 0
b11111 5

#2855000
0%
0+

