hw3/src/carry_lookahead_adder.v
module carry_lookahead_adder
#(
    parameter DATA_WIDTH = 16
)(
    input wire [DATA_WIDTH-1:0] iv_a,
    input wire [DATA_WIDTH-1:0] iv_b,
    input wire i_cin,
    output wire [DATA_WIDTH-1:0] ov_sum,
    output wire o_cout
);
    //
    // c0 = c0
    // c1 = g0 | p0.c0
    // c2 = g1 | p1.g0 | p1.p0.c0
    // c3 = g2 | p2.g1 | p2.p1.g0 | p2.p1.p0.c0
    // c4 = g3 | p3.g2 | p3.p2.g1 | p3.p2.p1.g0 | p3.p2.p1.p0.c0
    // c5 = g4 | p4.g3 | p4.p3.g2 | p4.p3.p2.g1 | p4.p3.p2.p1.g1 | p5.p4.p3.p2.p1.p0.c0
    // etc..
    //

    wire [DATA_WIDTH-1:0] p, g;
    wire [DATA_WIDTH:0] c;

    assign c[0] = i_cin;

    genvar i;

    // compute generate and propagation
    generate for (i = 0; i < DATA_WIDTH; i = i + 1) begin
        assign p[i] = iv_a[i] ^ iv_b[i];
        assign g[i] = iv_a[i] & iv_b[i];
    end endgenerate

    // compute carry for each stage
    generate for (i = 1; i < DATA_WIDTH+1; i = i + 1) begin
        assign c[i] = g[i-1] | ( p[i-1] & c[i-1] );
    end endgenerate

    // compute sum
    generate for (i = 0; i < DATA_WIDTH; i = i + 1) begin
        assign ov_sum[i] = p[i] ^ c[i];
    end endgenerate

    // assign final carry
    assign cout = c[DATA_WIDTH];

endmodule

hw3/src/carry_lookahead_adder_sync.v
module carry_lookahead_adder_sync
#(
    parameter DATA_WIDTH = 16
)(
    input wire i_clk,
    input wire i_rst,
    input wire i_en,
    input wire [DATA_WIDTH-1:0] iv_a,
    input wire [DATA_WIDTH-1:0] iv_b,
    input wire i_cin,
    output reg [DATA_WIDTH-1:0] ov_sum,
    output reg o_cout

);

    wire [DATA_WIDTH-1:0] comb_sum;
    wire comb_cout;

    always @(posedge i_clk) begin
        ov_sum <= ov_sum;
        o_cout <= o_cout;
        if (i_rst) begin
            ov_sum <= 0;
            o_cout <= 1'b0;
        end else if (i_en) begin
            ov_sum <= comb_sum;
            o_cout <= comb_cout;
        end
    end

    carry_lookahead_adder
    #(
        .DATA_WIDTH(DATA_WIDTH)
    ) cla (
        .iv_a(iv_a),
        .iv_b(iv_b),
        .i_cin(i_cin),
        .ov_sum(comb_sum),
        .o_cout(comb_cout)
    );

endmodule

hw3/verif/tb_adder.sv

module tb_adder;

    localparam DATA_WIDTH = 16;
    reg tb_clk;
    reg tb_rst;
    reg tb_en;
    reg [DATA_WIDTH-1:0] tb_a;
    reg [DATA_WIDTH-1:0] tb_b;
    reg tb_cin;
    wire [DATA_WIDTH-1:0] tb_sum;
    wire tb_cout;

    int num_errors = 0;
    logic tb_err;
    reg [DATA_WIDTH:0] tb_exp_sum;
    reg tb_exp_cout;

    carry_lookahead_adder_sync
    #(
        .DATA_WIDTH(DATA_WIDTH)
    ) clas (
        .i_clk(tb_clk),
        .i_rst(tb_rst),
        .i_en(tb_en),
        .iv_a(tb_a),
        .iv_b(tb_b),
        .i_cin(tb_cin),
        .ov_sum(tb_sum),
        .o_cout(tb_cout)
    );


    task assert_and_report(input [DATA_WIDTH-1:0] expected, input [DATA_WIDTH-1:0] actual);
    begin
        if (actual == expected) begin
            $display("SUCCESS!\n Expected: %b\n Actual:   %b", expected, actual);
            tb_err = 1'b0;
        end else begin
            $display("FAILURE!\n Expected: %b\n Actual:   %b", expected, actual);
            num_errors = num_errors + 1;
            tb_err = 1'bx;
        end
    end
    endtask // assert_and_report


    task test_add();
    begin
        $display("A: %h, B: %h, CIN: %h", tb_a, tb_b, tb_cin);
        {tb_exp_cout, tb_exp_sum} = {1'b0, tb_a} + {1'b0, tb_b} + { {(DATA_WIDTH){1'b0}}, tb_cin };
        assert_and_report( {tb_exp_cout, tb_exp_sum}, {tb_cout, tb_sum} );
    end
    endtask


    always #5 tb_clk = ~tb_clk;
    initial begin
        $dumpfile("waveform.vcd");
        $dumpvars;

        num_errors = 0;
        tb_clk = 1;
        tb_rst = 1;
        tb_en = 0;

        @(posedge tb_clk);
        tb_rst = 0;
        tb_en = 1;

        repeat (100) begin
            tb_a = $urandom();
            tb_b = $urandom();
            tb_cin = $urandom();
            @(posedge tb_clk);
            @(posedge tb_clk);
            test_add();
            $display();
        end

        $display();
        $display("Total number of errors: %d", num_errors);
        $display();

        $finish;
    end // initial
endmodule

hw3/sim/waveform.vcd
$date
   Tue Nov 12 16:09:03 2024
$end

$version
  2023.2.2
  $dumpfile ("waveform.vcd") 
$end

$timescale
  1ns
$end

$scope module tb_adder $end
$var reg 1 ! tb_clk $end
$var reg 1 " tb_rst $end
$var reg 1 # tb_en $end
$var reg 16 $ tb_a [15:0] $end
$var reg 16 % tb_b [15:0] $end
$var reg 1 & tb_cin $end
$var wire 16 ' tb_sum [15:0] $end
$var wire 1 ( tb_cout $end
$var reg 32 ) num_errors [31:0] $end
$var reg 1 * tb_err $end
$var reg 17 + tb_exp_sum [16:0] $end
$var reg 1 , tb_exp_cout $end
$scope module clas $end
$var wire 1 - i_clk $end
$var wire 1 . i_rst $end
$var wire 1 / i_en $end
$var wire 16 0 iv_a [15:0] $end
$var wire 16 1 iv_b [15:0] $end
$var wire 1 2 i_cin $end
$var reg 16 3 ov_sum [15:0] $end
$var reg 1 4 o_cout $end
$var wire 16 5 comb_sum [15:0] $end
$var wire 1 6 comb_cout $end
$scope module cla $end
$var wire 16 0 iv_a [15:0] $end
$var wire 16 1 iv_b [15:0] $end
$var wire 1 2 i_cin $end
$var wire 16 5 ov_sum [15:0] $end
$var wire 1 6 o_cout $end
$var wire 16 7 p [15:0] $end
$var wire 16 8 g [15:0] $end
$var wire 17 9 c [16:0] $end
$var wire 1 : cout $end
$upscope $end
$upscope $end
$scope task assert_and_report $end
$var reg 16 ; expected [15:0] $end
$var reg 16 < actual [15:0] $end
$upscope $end
$scope task test_add $end
$upscope $end
$upscope $end
$enddefinitions $end

#0
$dumpvars
1!
1"
0#
bx $
bx %
x&
b0 '
0(
b0 )
x*
bx +
x,
1-
1.
0/
bx 0
bx 1
x2
b0 3
04
bx 5
z6
bx 7
bx 8
bx 9
x:
bx ;
bx <
$end

#50
0!
0-

#100
1!
0"
1#
b11000111011011 $
b10010010111100 %
0&
bx '
z(
1-
0.
1/
b11000111011011 0
b10010010111100 1
02
bx 3
z4
b101011010010111 5
b1010101100111 7
b10000010011000 8
b100001111110000 9
0:

#150
0!
0-

#200
1!
b101011010010111 '
1-
b101011010010111 3

#250
0!
0-

#300
1!
b1100101010001110 $
b1111010011110000 %
1&
0*
b101011010010111 +
0,
1-
b1100101010001110 0
b1111010011110000 1
12
b1011111101111111 5
b11111001111110 7
b1100000010000000 8
b11000000100000001 9
1:
b101011010010111 ;
b101011010010111 <

#350
0!
0-

#400
1!
b1011111101111111 '
1-
b1011111101111111 3

#450
0!
0-

#500
1!
b1111111100011110 $
b10011011001011 %
b11011111101111111 +
1-
b1111111100011110 0
b10011011001011 1
b10010111101010 5
b1101100111010101 7
b10011000001010 8
b11111110000111111 9
1:
b1011111101111111 ;
b1011111101111111 <

#550
0!
0-

#600
1!
b10010111101010 '
1-
b10010111101010 3

#650
0!
0-

#700
1!
b1111000000011011 $
b1111000101011001 %
b10010010111101010 +
1-
b1111000000011011 0
b1111000101011001 1
b1110000101110101 5
b101000010 7
b1111000000011001 8
b11110000000110111 9
b10010111101010 ;
b10010111101010 <

#750
0!
0-

#800
1!
b1110000101110101 '
1-
b1110000101110101 3

#850
0!
0-

#900
1!
b1000111011111000 $
b1111000001111000 %
0&
b11110000101110101 +
1-
b1000111011111000 0
b1111000001111000 1
02
b111111101110000 5
b111111010000000 7
b1000000001111000 8
b10000000111110000 9
b1110000101110101 ;
b1110000101110101 <

#950
0!
0-

#1000
1!
b111111101110000 '
1-
b111111101110000 3

#1050
0!
0-

#1100
1!
b101001010010010 $
b1110000010010011 %
b10111111101110000 +
1-
b101001010010010 0
b1110000010010011 1
b11001100100101 5
b1011001000000001 7
b100000010010010 8
b11000000100100100 9
1:
b111111101110000 ;
b111111101110000 <

#1150
0!
0-

#1200
1!
b11001100100101 '
1-
b11001100100101 3

#1250
0!
0-

#1300
1!
b101100011011 $
b110111110001011 %
b10011001100100101 +
1-
b101100011011 0
b110111110001011 1
b111101010100110 5
b110010010010000 7
b101100001011 8
b1111000110110 9
0:
b11001100100101 ;
b11001100100101 <

#1350
0!
0-

#1400
1!
b111101010100110 '
1-
b111101010100110 3

#1450
0!
0-

#1500
1!
b1110101001110000 $
b1100001000011101 %
1&
b111101010100110 +
1-
b1110101001110000 0
b1100001000011101 1
12
b1010110010001110 5
b10100001101101 7
b1100001000010000 8
b11000010011100011 9
1:
b111101010100110 ;
b111101010100110 <

#1550
0!
0-

#1600
1!
b1010110010001110 '
1-
b1010110010001110 3

#1650
0!
0-

#1700
1!
b1011101100011110 $
b1100110100111001 %
0&
b11010110010001110 +
1-
b1011101100011110 0
b1100110100111001 1
02
b1000100001010111 5
b111011000100111 7
b1000100100011000 8
b11111111001110000 9
b1010110010001110 ;
b1010110010001110 <

#1750
0!
0-

#1800
1!
b1000100001010111 '
1-
b1000100001010111 3

#1850
0!
0-

#1900
1!
b111110001000100 $
b1011011110101001 %
b11000100001010111 +
1-
b111110001000100 0
b1011011110101001 1
b11001111101101 5
b1100101111101101 7
b11010000000000 8
b11111100000000000 9
b1000100001010111 ;
b1000100001010111 <

#1950
0!
0-

#2000
1!
b11001111101101 '
1-
b11001111101101 3

#2050
0!
0-

#2100
1!
b1110111111101 $
b111001011000111 %
1&
b10011001111101101 +
1-
b1110111111101 0
b111001011000111 1
12
b1001000011000101 5
b110111100111010 7
b1000011000101 8
b1111111111111111 9
0:
b11001111101101 ;
b11001111101101 <

#2150
0!
0-

#2200
1!
b1001000011000101 '
1-
b1001000011000101 3

#2250
0!
0-

#2300
1!
b10111101000001 $
b1110111100001011 %
0&
b1001000011000101 +
1-
b10111101000001 0
b1110111100001011 1
02
b1111001001100 5
b1100000001001010 7
b10111100000001 8
b11101111000000110 9
1:
b1001000011000101 ;
b1001000011000101 <

#2350
0!
0-

#2400
1!
b1111001001100 '
1-
b1111001001100 3

#2450
0!
0-

#2500
1!
b1010100011 $
b110100001000 %
1&
b10001111001001100 +
1-
b1010100011 0
b110100001000 1
12
b111110101100 5
b111110101011 7
b0 8
b111 9
0:
b1111001001100 ;
b1111001001100 <

#2550
0!
0-

#2600
1!
b111110101100 '
1-
b111110101100 3

#2650
0!
0-

#2700
1!
b1010001100111110 $
b11110001001001 %
0&
b111110101100 +
1-
b1010001100111110 0
b11110001001001 1
02
b1101111110000111 5
b1001111101110111 7
b10000000001000 8
b100000011110000 9
b111110101100 ;
b111110101100 <

#2750
0!
0-

#2800
1!
b1101111110000111 '
1-
b1101111110000111 3

#2850
0!
0-

#2900
1!
b1111101110000010 $
b11111011101101 %
b1101111110000111 +
1-
b1111101110000010 0
b11111011101101 1
b11101001101111 5
b1100010101101111 7
b11101010000000 8
b11111111100000000 9
1:
b1101111110000111 ;
b1101111110000111 <

#2950
0!
0-

#3000
1!
b11101001101111 '
1-
b11101001101111 3

#3050
0!
0-

#3100
1!
b1100011010001101 $
b1110001000101011 %
1&
b10011101001101111 +
1-
b1100011010001101 0
b1110001000101011 1
12
b1010100010111001 5
b10010010100110 7
b1100001000001001 8
b11000110000011111 9
b11101001101111 ;
b11101001101111 <

#3150
0!
0-

#3200
1!
b1010100010111001 '
1-
b1010100010111001 3

#3250
0!
0-

#3300
1!
b1000000010100011 $
b1101110110101110 %
0&
b11010100010111001 +
1-
b1000000010100011 0
b1101110110101110 1
02
b101111001010001 5
b101110100001101 7
b1000000010100010 8
b10000001101011100 9
b1010100010111001 ;
b1010100010111001 <

#3350
0!
0-

#3400
1!
b101111001010001 '
1-
b101111001010001 3

#3450
0!
0-

#3500
1!
b100011111000001 $
b1010010000111011 %
b10101111001010001 +
1-
b100011111000001 0
b1010010000111011 1
b1110101111111100 5
b1110001111111010 7
b10000000001 8
b100000000110 9
0:
b101111001010001 ;
b101111001010001 <

#3550
0!
0-

#3600
1!
b1110101111111100 '
1-
b1110101111111100 3

#3650
0!
0-

#3700
1!
b100101100101001 $
b10010011011111 %
b1110101111111100 +
1-
b100101100101001 0
b10010011011111 1
b111000000001000 5
b110111111110110 7
b1001 8
b1111111111110 9
b1110101111111100 ;
b1110101111111100 <

#3750
0!
0-

#3800
1!
b111000000001000 '
1-
b111000000001000 3

#3850
0!
0-

#3900
1!
b1000110101111101 $
b110110010100000 %
1&
b111000000001000 +
1-
b1000110101111101 0
b110110010100000 1
12
b1111101000011110 5
b1110000111011101 7
b110000100000 8
b1101111000011 9
b111000000001000 ;
b111000000001000 <

#3950
0!
0-

#4000
1!
b1111101000011110 '
1-
b1111101000011110 3

#4050
0!
0-

#4100
1!
b1011000111111101 $
b1011011111001001 %
0&
b1111101000011110 +
1-
b1011000111111101 0
b1011011111001001 1
02
b110100111000110 5
b11000110100 7
b1011000111001001 8
b10110111111110010 9
1:
b1111101000011110 ;
b1111101000011110 <

#4150
0!
0-

#4200
1!
b110100111000110 '
1-
b110100111000110 3

#4250
0!
0-

#4300
1!
b1011010000101011 $
b100010101000111 %
1&
b10110100111000110 +
1-
b1011010000101011 0
b100010101000111 1
12
b1111100101110011 5
b1111000101101100 7
b10000000011 8
b100000011111 9
0:
b110100111000110 ;
b110100111000110 <

#4350
0!
0-

#4400
1!
b1111100101110011 '
1-
b1111100101110011 3

#4450
0!
0-

#4500
1!
b101101010010101 $
b1111011101000100 %
0&
b1111100101110011 +
1-
b101101010010101 0
b1111011101000100 1
02
b101000111011001 5
b1010110111010001 7
b101001000000100 8
b11111110000001000 9
1:
b1111100101110011 ;
b1111100101110011 <

#4550
0!
0-

#4600
1!
b101000111011001 '
1-
b101000111011001 3

#4650
0!
0-

#4700
1!
b10010111011101 $
b1010101101110000 %
1&
b10101000111011001 +
1-
b10010111011101 0
b1010101101110000 1
12
b1101000101001110 5
b1000111010101101 7
b10000101010000 8
b101111111100011 9
0:
b101000111011001 ;
b101000111011001 <

#4750
0!
0-

#4800
1!
b1101000101001110 '
1-
b1101000101001110 3

#4850
0!
0-

#4900
1!
b101110111000110 $
b11000000101 %
0&
b1101000101001110 +
1-
b101110111000110 0
b11000000101 1
02
b110001111001011 5
b101101111000011 7
b10000000100 8
b11100000001000 9
b1101000101001110 ;
b1101000101001110 <

#4950
0!
0-

#5000
1!
b110001111001011 '
1-
b110001111001011 3

#5050
0!
0-

#5100
1!
b100110101111001 $
b10101111100010 %
b110001111001011 +
1-
b100110101111001 0
b10101111100010 1
b111100101011011 5
b110011010011011 7
b100101100000 8
b1111111000000 9
b110001111001011 ;
b110001111001011 <

#5150
0!
0-

#5200
1!
b111100101011011 '
1-
b111100101011011 3

#5250
0!
0-

#5300
1!
b1000001001110010 $
b1000100110101001 %
1&
b111100101011011 +
1-
b1000001001110010 0
b1000100110101001 1
12
b110000011100 5
b101111011011 7
b1000000000100000 8
b10000011111000111 9
1:
b111100101011011 ;
b111100101011011 <

#5350
0!
0-

#5400
1!
b110000011100 '
1-
b110000011100 3

#5450
0!
0-

#5500
1!
b1010111010110000 $
b1101011100100010 %
b10000110000011100 +
1-
b1010111010110000 0
b1101011100100010 1
b1000010111010011 5
b111100110010010 7
b1000011000100000 8
b11111110001000001 9
b110000011100 ;
b110000011100 <

#5550
0!
0-

#5600
1!
b1000010111010011 '
1-
b1000010111010011 3

#5650
0!
0-

#5700
1!
b1000011001011110 $
b101100110010100 %
0&
b11000010111010011 +
1-
b1000011001011110 0
b101100110010100 1
02
b1101111111110010 5
b1101111111001010 7
b10100 8
b111000 9
0:
b1000010111010011 ;
b1000010111010011 <

#5750
0!
0-

#5800
1!
b1101111111110010 '
1-
b1101111111110010 3

#5850
0!
0-

#5900
1!
b110010000010001 $
b100001000101 %
b1101111111110010 +
1-
b110010000010001 0
b100001000101 1
b110110001010110 5
b110110001010100 7
b1 8
b10 9
b1101111111110010 ;
b1101111111110010 <

#5950
0!
0-

#6000
1!
b110110001010110 '
1-
b110110001010110 3

#6050
0!
0-

#6100
1!
b110110110100111 $
b1000111010100011 %
1&
b110110001010110 +
1-
b110110110100111 0
b1000111010100011 1
12
b1111110001001011 5
b1110001100000100 7
b110010100011 8
b1111101001111 9
b110110001010110 ;
b110110001010110 <

#6150
0!
0-

#6200
1!
b1111110001001011 '
1-
b1111110001001011 3

#6250
0!
0-

#6300
1!
b11100101 $
b1111001010110101 %
0&
b1111110001001011 +
1-
b11100101 0
b1111001010110101 1
02
b1111001110011010 5
b1111001001010000 7
b10100101 8
b111001010 9
0:
b1111110001001011 ;
b1111110001001011 <

#6350
0!
0-

#6400
1!
b1111001110011010 '
1-
b1111001110011010 3

#6450
0!
0-

#6500
1!
b110101101000110 $
b110000001011100 %
1&
b1111001110011010 +
1-
b110101101000110 0
b110000001011100 1
12
b1100101110100011 5
b101100011010 7
b110000001000100 8
b1100000010111001 9
b1111001110011010 ;
b1111001110011010 <

#6550
0!
0-

#6600
1!
b1100101110100011 '
1-
b1100101110100011 3

#6650
0!
0-

#6700
1!
b10111100111011 $
b110000101000001 %
0&
b1100101110100011 +
1-
b10111100111011 0
b110000101000001 1
02
b1001000001111100 5
b100111001111010 7
b10000100000001 8
b1101111000000110 9
b1100101110100011 ;
b1100101110100011 <

#6750
0!
0-

#6800
1!
b1001000001111100 '
1-
b1001000001111100 3

#6850
0!
0-

#6900
1!
b1111101101110101 $
b1100110010000111 %
b1001000001111100 +
1-
b1111101101110101 0
b1100110010000111 1
b1100011111111100 5
b11011111110010 7
b1100100000000101 8
b11111000000001110 9
1:
b1001000001111100 ;
b1001000001111100 <

#6950
0!
0-

#7000
1!
b1100011111111100 '
1-
b1100011111111100 3

#7050
0!
0-

#7100
1!
b101011001010010 $
b1111101111000010 %
b11100011111111100 +
1-
b101011001010010 0
b1111101111000010 1
b101001000010100 5
b1010110110010000 7
b101001001000010 8
b11111111110000100 9
b1100011111111100 ;
b1100011111111100 <

#7150
0!
0-

#7200
1!
b101001000010100 '
1-
b101001000010100 3

#7250
0!
0-

#7300
1!
b1010001111100101 $
b1111011100110111 %
1&
b10101001000010100 +
1-
b1010001111100101 0
b1111011100110111 1
12
b1001101100011101 5
b101010011010010 7
b1010001100100101 8
b11100111111001111 9
b101001000010100 ;
b101001000010100 <

#7350
0!
0-

#7400
1!
b1001101100011101 '
1-
b1001101100011101 3

#7450
0!
0-

#7500
1!
b101000111010011 $
b100110110001010 %
0&
b11001101100011101 +
1-
b101000111010011 0
b100110110001010 1
02
b1001111101011101 5
b1110001011001 7
b100000110000010 8
b1000001100000100 9
0:
b1001101100011101 ;
b1001101100011101 <

#7550
0!
0-

#7600
1!
b1001111101011101 '
1-
b1001111101011101 3

#7650
0!
0-

#7700
1!
b110000100000011 $
b1111000101101111 %
1&
b1001111101011101 +
1-
b110000100000011 0
b1111000101101111 1
12
b101001001110011 5
b1001000001101100 7
b110000100000011 8
b11100001000011111 9
1:
b1001111101011101 ;
b1001111101011101 <

#7750
0!
0-

#7800
1!
b101001001110011 '
1-
b101001001110011 3

#7850
0!
0-

#7900
1!
b11110010111011 $
b100001101000010 %
b10101001001110011 +
1-
b11110010111011 0
b100001101000010 1
b111111111111110 5
b111111111111001 7
b10 8
b111 9
0:
b101001001110011 ;
b101001001110011 <

#7950
0!
0-

#8000
1!
b111111111111110 '
1-
b111111111111110 3

#8050
0!
0-

#8100
1!
b1010000110101 $
b1010010001000110 %
0&
b111111111111110 +
1-
b1010000110101 0
b1010010001000110 1
02
b1011100001111011 5
b1011000001110011 7
b10000000100 8
b100000001000 9
b111111111111110 ;
b111111111111110 <

#8150
0!
0-

#8200
1!
b1011100001111011 '
1-
b1011100001111011 3

#8250
0!
0-

#8300
1!
b1110001011100110 $
b1110000100000001 %
1&
b1011100001111011 +
1-
b1110001011100110 0
b1110000100000001 1
12
b1100001111101000 5
b1111100111 7
b1110000000000000 8
b11100000000001111 9
1:
b1011100001111011 ;
b1011100001111011 <

#8350
0!
0-

#8400
1!
b1100001111101000 '
1-
b1100001111101000 3

#8450
0!
0-

#8500
1!
b1111111100100010 $
b1111010100110110 %
b11100001111101000 +
1-
b1111111100100010 0
b1111010100110110 1
b1111010001011001 5
b101000010100 7
b1111010100100010 8
b11111111001001101 9
b1100001111101000 ;
b1100001111101000 <

#8550
0!
0-

#8600
1!
b1111010001011001 '
1-
b1111010001011001 3

#8650
0!
0-

#8700
1!
b110011001100 $
b1101100000011100 %
0&
b11111010001011001 +
1-
b110011001100 0
b1101100000011100 1
02
b1110010011101000 5
b1101010011010000 7
b100000001100 8
b11000000111000 9
0:
b1111010001011001 ;
b1111010001011001 <

#8750
0!
0-

#8800
1!
b1110010011101000 '
1-
b1110010011101000 3

#8850
0!
0-

#8900
1!
b101110110111001 $
b1101011100111110 %
b1110010011101000 +
1-
b101110110111001 0
b1101011100111110 1
b11010011110111 5
b1000101010000111 7
b101010100111000 8
b11011111001110000 9
1:
b1110010011101000 ;
b1110010011101000 <

#8950
0!
0-

#9000
1!
b11010011110111 '
1-
b11010011110111 3

#9050
0!
0-

#9100
1!
b101001011101100 $
b1110010000001011 %
b10011010011110111 +
1-
b101001011101100 0
b1110010000001011 1
b11011011110111 5
b1011011011100111 7
b100000000001000 8
b11000000000010000 9
b11010011110111 ;
b11010011110111 <

#9150
0!
0-

#9200
1!
b11011011110111 '
1-
b11011011110111 3

#9250
0!
0-

#9300
1!
b10100100100000 $
b100000111000100 %
1&
b10011011011110111 +
1-
b10100100100000 0
b100000111000100 1
12
b110101011100101 5
b110100011100100 7
b100000000 8
b1000000001 9
0:
b11011011110111 ;
b11011011110111 <

#9350
0!
0-

#9400
1!
b110101011100101 '
1-
b110101011100101 3

#9450
0!
0-

#9500
1!
b1111010010001010 $
b1001010010110001 %
0&
b110101011100101 +
1-
b1111010010001010 0
b1001010010110001 1
02
b1000100100111011 5
b110000000111011 7
b1001010010000000 8
b11110100100000000 9
1:
b110101011100101 ;
b110101011100101 <

#9550
0!
0-

#9600
1!
b1000100100111011 '
1-
b1000100100111011 3

#9650
0!
0-

#9700
1!
b1001100000010001 $
b1011110111010001 %
b11000100100111011 +
1-
b1001100000010001 0
b1011110111010001 1
b101010111100010 5
b10010111000000 7
b1001100000010001 8
b10111000000100010 9
b1000100100111011 ;
b1000100100111011 <

#9750
0!
0-

#9800
1!
b101010111100010 '
1-
b101010111100010 3

#9850
0!
0-

#9900
1!
b1001011010110 $
b1011001001011100 %
1&
b10101010111100010 +
1-
b1001011010110 0
b1011001001011100 1
12
b1100010100110011 5
b1010000010001010 7
b1001001010100 8
b110010110111001 9
0:
b101010111100010 ;
b101010111100010 <

#9950
0!
0-

#10000
1!
b1100010100110011 '
1-
b1100010100110011 3

#10050
0!
0-

#10100
1!
b111000110100110 $
b100101001101101 %
b1100010100110011 +
1-
b111000110100110 0
b100101001101101 1
b1011110000010100 5
b11101111001011 7
b100000000100100 8
b1000011111011111 9
b1100010100110011 ;
b1100010100110011 <

#10150
0!
0-

#10200
1!
b1011110000010100 '
1-
b1011110000010100 3

#10250
0!
0-

#10300
1!
b1001000111010 $
b101110101000011 %
b1011110000010100 +
1-
b1001000111010 0
b101110101000011 1
b110111101111110 5
b100111101111001 7
b1000000000010 8
b10000000000111 9
b1011110000010100 ;
b1011110000010100 <

#10350
0!
0-

#10400
1!
b110111101111110 '
1-
b110111101111110 3

#10450
0!
0-

#10500
1!
b100011110000000 $
b1100111011101001 %
0&
b110111101111110 +
1-
b100011110000000 0
b1100111011101001 1
02
b1011001101001 5
b1000100101101001 7
b100011010000000 8
b11001111100000000 9
1:
b110111101111110 ;
b110111101111110 <

#10550
0!
0-

#10600
1!
b1011001101001 '
1-
b1011001101001 3

#10650
0!
0-

#10700
1!
b11101010010111 $
b1110000100100011 %
1&
b10001011001101001 +
1-
b11101010010111 0
b1110000100100011 1
12
b1101110111011 5
b1101101110110100 7
b10000000000011 8
b11100000000001111 9
1:
b1011001101001 ;
b1011001101001 <

#10750
0!
0-

#10800
1!
b1101110111011 '
1-
b1101110111011 3

#10850
0!
0-

#10900
1!
b1110000000001010 $
b10100010100011 %
0&
b10001101110111011 +
1-
b1110000000001010 0
b10100010100011 1
02
b100010101101 5
b1100100010101001 7
b10000000000010 8
b11100000000000100 9
b1101110111011 ;
b1101110111011 <

#10950
0!
0-

#11000
1!
b100010101101 '
1-
b100010101101 3

#11050
0!
0-

#11100
1!
b1100111111101010 $
b110001100111010 %
1&
b10000100010101101 +
1-
b1100111111101010 0
b110001100111010 1
12
b11001100100101 5
b1010110011010000 7
b100001100101010 8
b11001111111110101 9
b100010101101 ;
b100010101101 <

#11150
0!
0-

#11200
1!
b11001100100101 '
1-
b11001100100101 3

#11250
0!
0-

#11300
1!
b1110100001101 $
b100001101000100 %
b10011001100100101 +
1-
b1110100001101 0
b100001101000100 1
b110000001010010 5
b101111001001001 7
b100000100 8
b11111000011011 9
0:
b11001100100101 ;
b11001100100101 <

#11350
0!
0-

#11400
1!
b110000001010010 '
1-
b110000001010010 3

#11450
0!
0-

#11500
1!
b11100100011001 $
b1001100101110 %
b110000001010010 +
1-
b11100100011001 0
b1001100101110 1
b100110001001000 5
b10101000110111 7
b1000100001000 8
b110011001111111 9
b110000001010010 ;
b110000001010010 <

#11550
0!
0-

#11600
1!
b100110001001000 '
1-
b100110001001000 3

#11650
0!
0-

#11700
1!
b11011001001000 $
b11000000111011 %
0&
b100110001001000 +
1-
b11011001001000 0
b11000000111011 1
02
b110011010000011 5
b11001110011 7
b11000000001000 8
b110000011110000 9
b100110001001000 ;
b100110001001000 <

#11750
0!
0-

#11800
1!
b110011010000011 '
1-
b110011010000011 3

#11850
0!
0-

#11900
1!
b101110000011011 $
b110100101010100 %
b110011010000011 +
1-
b101110000011011 0
b110100101010100 1
b1100010101101111 5
b11010101001111 7
b100100000010000 8
b1111000000100000 9
b110011010000011 ;
b110011010000011 <

#11950
0!
0-

#12000
1!
b1100010101101111 '
1-
b1100010101101111 3

#12050
0!
0-

#12100
1!
b1110010100101001 $
b1001111110011101 %
b1100010101101111 +
1-
b1110010100101001 0
b1001111110011101 1
b1000010011000110 5
b111101010110100 7
b1000010100001001 8
b11111111001110010 9
1:
b1100010101101111 ;
b1100010101101111 <

#12150
0!
0-

#12200
1!
b1000010011000110 '
1-
b1000010011000110 3

#12250
0!
0-

#12300
1!
b1011000101111011 $
b1111101110111000 %
b11000010011000110 +
1-
b1011000101111011 0
b1111101110111000 1
b1010110100110011 5
b100101011000011 7
b1011000100111000 8
b11110011111110000 9
b1000010011000110 ;
b1000010011000110 <

#12350
0!
0-

#12400
1!
b1010110100110011 '
1-
b1010110100110011 3

#12450
0!
0-

#12500
1!
b1001000011111011 $
b1110000011100001 %
1&
b11010110100110011 +
1-
b1001000011111011 0
b1110000011100001 1
12
b111000111011101 5
b111000000011010 7
b1000000011100001 8
b10000000111000111 9
b1010110100110011 ;
b1010110100110011 <

#12550
0!
0-

#12600
1!
b111000111011101 '
1-
b111000111011101 3

#12650
0!
0-

#12700
1!
b1010000010110111 $
b1001001001011100 %
0&
b10111000111011101 +
1-
b1010000010110111 0
b1001001001011100 1
02
b11001100010011 5
b11001011101011 7
b1000000000010100 8
b10000000111111000 9
b111000111011101 ;
b111000111011101 <

#12750
0!
0-

#12800
1!
b11001100010011 '
1-
b11001100010011 3

#12850
0!
0-

#12900
1!
b1100111001000 $
b10001101011000 %
1&
b10011001100010011 +
1-
b1100111001000 0
b10001101011000 1
12
b11110100100001 5
b11101010010000 7
b101001000 8
b11110110001 9
0:
b11001100010011 ;
b11001100010011 <

#12950
0!
0-

#13000
1!
b11110100100001 '
1-
b11110100100001 3

#13050
0!
0-

#13100
1!
b11001001110101 $
b1100010000001111 %
0&
b11110100100001 +
1-
b11001001110101 0
b1100010000001111 1
02
b1111011010000100 5
b1111011001111010 7
b101 8
b11111110 9
b11110100100001 ;
b11110100100001 <

#13150
0!
0-

#13200
1!
b1111011010000100 '
1-
b1111011010000100 3

#13250
0!
0-

#13300
1!
b100011011011011 $
b1101110111010111 %
b1111011010000100 +
1-
b100011011011011 0
b1101110111010111 1
b10010010110010 5
b1001101100001100 7
b100010011010011 8
b11011111110111110 9
1:
b1111011010000100 ;
b1111011010000100 <

#13350
0!
0-

#13400
1!
b10010010110010 '
1-
b10010010110010 3

#13450
0!
0-

#13500
1!
b11110000100011 $
b1000001001101 %
1&
b10010010010110010 +
1-
b11110000100011 0
b1000001001101 1
12
b100110001110001 5
b10110001101110 7
b1000000000001 8
b110000000011111 9
0:
b10010010110010 ;
b10010010110010 <

#13550
0!
0-

#13600
1!
b100110001110001 '
1-
b100110001110001 3

#13650
0!
0-

#13700
1!
b1100001111000111 $
b101011100101000 %
b100110001110001 +
1-
b1100001111000111 0
b101011100101000 1
b1101011110000 5
b1001010011101111 7
b100001100000000 8
b11000111000011111 9
1:
b100110001110001 ;
b100110001110001 <

#13750
0!
0-

#13800
1!
b1101011110000 '
1-
b1101011110000 3

#13850
0!
0-

#13900
1!
b110111011000011 $
b1001001101001011 %
0&
b10001101011110000 +
1-
b110111011000011 0
b1001001101001011 1
02
b1000001110 5
b1111110110001000 7
b1001000011 8
b11111111110000110 9
1:
b1101011110000 ;
b1101011110000 <

#13950
0!
0-

#14000
1!
b1000001110 '
1-
b1000001110 3

#14050
0!
0-

#14100
1!
b1101110111001110 $
b101011100010010 %
b10000001000001110 +
1-
b1101110111001110 0
b101011100010010 1
b11010011100000 5
b1000101011011100 7
b101010100000010 8
b11011111000111100 9
b1000001110 ;
b1000001110 <

#14150
0!
0-

#14200
1!
b11010011100000 '
1-
b11010011100000 3

