hw1/src/alu.v
// alu.v
// 32-bit ALU
//
// ALUOps:
// 000: and
// 001: or
// 010: add
// 011: sub
// 100: slt (shift if less than)
// default: 0

module alu (
    input [31:0] A, B,
    input [2:0] ALUOp,
    output [31:0] Q,
    output Cout
);


always @(*)
begin
    case (ALUOp)
        3'b000: // logical and
            Q = A & B;
        3'b001: // logical or
            Q = A | B;
        3'b010: // addition
            Q = A + B;
        3'b011: // subtraction
            Q = A - B;
        3'b100: // set if A less than B
            if (A < B) begin
                Q = 32'd1;
            end else begin
                Q = 32'd0;
            end
        default:
            Q = 32'd0;
    endcase
end

endmodule

hw1/verif/tb_alu.sv
// tb_alu.sv
//
// https://www.asic-world.com/systemverilog/system_task_function4.html

module tb_alu;

    localparam DATA_WIDTH = 32;
    int num_errors = 0;

    // inputs
    reg [DATA_WIDTH-1:0] A, B;
    reg [2:0] ALUOp;

    // outputs
    wire [DATA_WIDTH-1:0] Q;
    // wire Cout;

    // instantiation unit under test 
    alu #(.DATA_WIDTH(DATA_WIDTH)) dut (
        .A(A),
        .B(B),
        .ALUOp(ALUOp),
        .Q(Q)
        // .Cout(Cout)
    );

    reg [DATA_WIDTH-1:0] exp;
    reg clk;
    always #5 clk = ~clk;

    initial begin
        $dumpfile("waveform.vcd");
        $dumpvars;

        clk = 0;
        exp = { (DATA_WIDTH){1'bx} };

        A = 32'd1;
        B = 32'd2;
        exp = 3;
        ALUOp = 3'b010;
        #10;
        $display("A = %h, B = %h, ALUOp = %b", A, B, ALUOp);
        assert(Q == exp) $display("SUCCESS! Expected: %h. Actual: %h", Q, exp);
        else $error("FAILED! Expected: %h. Actual: %h", Q, exp);
        $display();


        A = 32'd3;
        B = 32'd4;
        exp = -1;
        ALUOp = 3'b110;
        #10;
        $display("A = %h, B = %h, ALUOp = %b", A, B, ALUOp);
        assert(Q == exp) $display("SUCCESS! Expected: %h. Actual: %h", Q, exp);
        else $error("FAILED! Expected: %h. Actual: %h", Q, exp);
        $display();

        // Apply stimulus for 10 clock cycles;
        repeat (100) begin
            A = $urandom();
            B = $urandom();
            ALUOp = $urandom();

            #10; // Wait for rising edge clock 

            $display("A = %h, B = %h, ALUOp = %b", A, B, ALUOp);
            case (ALUOp)
                3'b000: begin
                    exp = A & B;
                    assert(Q == exp) $display("SUCCESS! Expected: %h. Actual: %h", Q, exp);
                    else begin $error("FAILED! Expected: %h. Actual: %h", Q, exp); num_errors = num_errors + 1; end
                end
                3'b001: begin
                    exp = A | B;
                    assert(Q == exp) $display("SUCCESS! Expected: %h. Actual: %h", Q, exp);
                    else begin $error("FAILED! Expected: %h. Actual: %h", Q, exp); num_errors = num_errors + 1; end
                end
                3'b010: begin
                    exp = A + B;
                    assert(Q == exp) $display("SUCCESS! Expected: %h. Actual: %h", Q, exp);
                    else begin $error("FAILED! Expected: %h. Actual: %h", Q, exp); num_errors = num_errors + 1; end
                end
                3'b110: begin
                    exp = A - B;
                    assert(Q == exp) $display("SUCCESS! Expected: %h. Actual: %h", Q, exp);
                    else begin $error("FAILED! Expected: %h. Actual: %h", Q, exp); num_errors = num_errors + 1; end
                end
                3'b111: begin
                    if (A < B) begin
                        exp = { { (DATA_WIDTH-1){1'b0} }, 1'b1}; // exp = 1
                    end else begin
                        exp = { (DATA_WIDTH){1'b0} }; // exp = 0
                    end
                    assert(Q == exp) $display("SUCCESS! Expected: %h. Actual: %h", Q, exp);
                    else begin $error("FAILED! Expected: %h. Actual: %h", Q, exp); num_errors = num_errors + 1; end
                end
                default: begin
                    exp = 0;
                    assert(Q == exp) $display("SUCCESS! Expected: %h. Actual: %h", Q, exp);
                    else begin $error("FAILED! Expected: %h. Actual: %h", Q, exp); num_errors = num_errors + 1; end
                end
            endcase

            $display();

        end // repeat

        $display();
        $display("Total number of errors: %d", num_errors);
        $display();

        $finish;
    end // initial
endmodule

hw1/run/waveform.vcd
$date
   Sun Oct 13 13:41:14 2024
$end

$version
  2023.2.2
  $dumpfile ("waveform.vcd") 
$end

$timescale
  1ps
$end

$scope module tb_alu $end
$var reg 32 ! num_errors [31:0] $end
$var reg 32 " A [31:0] $end
$var reg 32 # B [31:0] $end
$var reg 3 $ ALUOp [2:0] $end
$var wire 32 % Q [31:0] $end
$var reg 32 & exp [31:0] $end
$var reg 1 ' clk $end
$scope module dut $end
$var wire 32 ( A [31:0] $end
$var wire 32 ) B [31:0] $end
$var wire 3 * ALUOp [2:0] $end
$var reg 32 + Q [31:0] $end
$upscope $end
$upscope $end
$enddefinitions $end

#0
$dumpvars
b0 !
b1 "
b10 #
b10 $
b11 %
b11 &
0'
b1 (
b10 )
b10 *
b11 +
$end

#5000
1'

#10000
b11 "
b100 #
b110 $
b11111111111111111111111111111111 %
b11111111111111111111111111111111 &
0'
b11 (
b100 )
b110 *
b11111111111111111111111111111111 +

#15000
1'

#20000
b1100100110010010011000111011011 "
b1101111101000010010010010111100 #
b100 $
b0 %
0'
b1100100110010010011000111011011 (
b1101111101000010010010010111100 )
b100 *
b0 +

#25000
1'

#30000
b1000110100011001100101010001110 "
b1101011001111001111010011110000 #
b101 $
b0 &
0'
b1000110100011001100101010001110 (
b1101011001111001111010011110000 )
b101 *

#35000
1'

#40000
b10110100110111111111100011110 "
b1010000000001100010011011001011 #
b1 $
b1010110100111111111111111011111 %
0'
b10110100110111111111100011110 (
b1010000000001100010011011001011 )
b1 *
b1010110100111111111111111011111 +

#45000
1'

#50000
b1101011110110101111000000011011 "
b10110100100101111000101011001 #
b1111111110110101111000101011011 %
b1010110100111111111111111011111 &
0'
b1101011110110101111000000011011 (
b10110100100101111000101011001 )
b1111111110110101111000101011011 +

#55000
1'

#60000
b1000100110111001000111011111000 "
b10101101001011101111000001111000 #
b100 $
b0 %
b1111111110110101111000101011011 &
0'
b1000100110111001000111011111000 (
b10101101001011101111000001111000 )
b100 *
b0 +

#65000
1'

#70000
b10001101011111110101001010010010 "
b10011001000010011110000010010011 #
b110 $
b11110100011101010111000111111111 %
b0 &
0'
b10001101011111110101001010010010 (
b10011001000010011110000010010011 )
b110 *
b11110100011101010111000111111111 +

#75000
1'

#80000
b1000001010111110000101100011011 "
b1011101111001100110111110001011 #
b11100011011110001001101110010000 %
b11110100011101010111000111111111 &
0'
b1000001010111110000101100011011 (
b1011101111001100110111110001011 )
b11100011011110001001101110010000 +

#85000
1'

#90000
b1000101010001001110101001110000 "
b1101011011001011100001000011101 #
b1 $
b1101111011001011110101001111101 %
b11100011011110001001101110010000 &
0'
b1000101010001001110101001110000 (
b1101011011001011100001000011101 )
b1 *
b1101111011001011110101001111101 +

#95000
1'

#100000
b1011111101111011011101100011110 "
b10101100110001001100110100111001 #
b100 $
b0 %
b1101111011001011110101001111101 &
0'
b1011111101111011011101100011110 (
b10101100110001001100110100111001 )
b100 *
b0 +

#105000
1'

#110000
b10100111011001010111110001000100 "
b1110010000010011011011110101001 #
b10 $
b11001011011110011001111101101 %
b0 &
0'
b10100111011001010111110001000100 (
b1110010000010011011011110101001 )
b10 *
b11001011011110011001111101101 +

#115000
1'

#120000
b10001000000101110001110111111101 "
b1010001110001110111001011000111 #
b11 $
b0 %
b11001011011110011001111101101 &
0'
b10001000000101110001110111111101 (
b1010001110001110111001011000111 )
b11 *
b0 +

#125000
1'

#130000
b1000110101011110010111101000001 "
b1111001001011001110111100001011 #
b100 $
b0 &
0'
b1000110101011110010111101000001 (
b1111001001011001110111100001011 )
b100 *

#135000
1'

#140000
b1110000101011010000001010100011 "
b10000001010001000000110100001000 #
b11 $
0'
b1110000101011010000001010100011 (
b10000001010001000000110100001000 )
b11 *

#145000
1'

#150000
b1000111011011111010001100111110 "
b1000111111100110011110001001001 #
b110 $
b11111111011111000110011011110101 %
0'
b1000111011011111010001100111110 (
b1000111111100110011110001001001 )
b110 *
b11111111011111000110011011110101 +

#155000
1'

#160000
b10000001110111111101110000010 "
b10111000101000000011111011101101 #
b1010111100110111011110010010101 %
b11111111011111000110011011110101 &
0'
b10000001110111111101110000010 (
b10111000101000000011111011101101 )
b1010111100110111011110010010101 +

#165000
1'

#170000
b101010110011111100011010001101 "
b11111110001000101011 #
b111 $
b0 %
b1010111100110111011110010010101 &
0'
b101010110011111100011010001101 (
b11111110001000101011 )
b111 *
b0 +

#175000
1'

#180000
b111110100100001000000010100011 "
b10010000010010111101110110101110 #
b100 $
b0 &
0'
b111110100100001000000010100011 (
b10010000010010111101110110101110 )
b100 *

#185000
1'

#190000
b1010011100101010100011111000001 "
b111011000110111010010000111011 #
b0 $
b10011000100010000010000000001 %
0'
b1010011100101010100011111000001 (
b111011000110111010010000111011 )
b0 *
b10011000100010000010000000001 +

#195000
1'

#200000
b10110000100011010100101100101001 "
b1111001101011000010010011011111 #
b110 $
b110110111000010010011001001010 %
b10011000100010000010000000001 &
0'
b10110000100011010100101100101001 (
b1111001101011000010010011011111 )
b110 *
b110110111000010010011001001010 +

#205000
1'

#210000
b1000110001001011000110101111101 "
b1001101010000010110110010100000 #
b1 $
b1001111011001011110110111111101 %
b110110111000010010011001001010 &
0'
b1000110001001011000110101111101 (
b1001101010000010110110010100000 )
b1 *
b1001111011001011110110111111101 +

#215000
1'

#220000
b1011011110011011011000111111101 "
b1111101110011101011011111001001 #
b0 $
b1011001110011001011000111001001 %
b1001111011001011110110111111101 &
0'
b1011011110011011011000111111101 (
b1111101110011101011011111001001 )
b0 *
b1011001110011001011000111001001 +

#225000
1'

#230000
b1110000011011010000101011 "
b1000011111101000100010101000111 #
b1 $
b1000011111101011111010101101111 %
b1011001110011001011000111001001 &
0'
b1110000011011010000101011 (
b1000011111101000100010101000111 )
b1 *
b1000011111101011111010101101111 +

#235000
1'

#240000
b1100010110100010101101010010101 "
b11111110000011111011101000100 #
b10 $
b10000010100100110101000111011001 %
b1000011111101011111010101101111 &
0'
b1100010110100010101101010010101 (
b11111110000011111011101000100 )
b10 *
b10000010100100110101000111011001 +

#245000
1'

#250000
b111101100011010010010111011101 "
b10100001100000111010101101110000 #
b1 $
b10111101100011111010111111111101 %
b10000010100100110101000111011001 &
0'
b111101100011010010010111011101 (
b10100001100000111010101101110000 )
b1 *
b10111101100011111010111111111101 +

#255000
1'

#260000
b1100101100010100101110111000110 "
b10000100010101010000011000000101 #
b110 $
b11100001001101010101011111000001 %
b10111101100011111010111111111101 &
0'
b1100101100010100101110111000110 (
b10000100010101010000011000000101 )
b110 *
b11100001001101010101011111000001 +

#265000
1'

#270000
b10001011010101100100110101111001 "
b1000001111000100010101111100010 #
b1001001011101000010000110010111 %
b11100001001101010101011111000001 &
0'
b10001011010101100100110101111001 (
b1000001111000100010101111100010 )
b1001001011101000010000110010111 +

#275000
1'

#280000
b1110101000101101000001001110010 "
b10100111011011001000100110101001 #
b11 $
b0 %
b1001001011101000010000110010111 &
0'
b1110101000101101000001001110010 (
b10100111011011001000100110101001 )
b11 *
b0 +

#285000
1'

#290000
b1111110100110001010111010110000 "
b10110010110000101101011100100010 #
b101 $
b0 &
0'
b1111110100110001010111010110000 (
b10110010110000101101011100100010 )
b101 *

#295000
1'

#300000
b101001100111101000011001011110 "
b100111110110010101100110010100 #
b110 $
b1110001010010110011001010 %
0'
b101001100111101000011001011110 (
b100111110110010101100110010100 )
b110 *
b1110001010010110011001010 +

#305000
1'

#310000
b1011000111110010110010000010001 "
b10100110011100100000100001000101 #
b0 $
b11100000000000000000001 %
b1110001010010110011001010 &
0'
b1011000111110010110010000010001 (
b10100110011100100000100001000101 )
b0 *
b11100000000000000000001 +

#315000
1'

#320000
b1001010001101100110110110100111 "
b1010000000100001000111010100011 #
b101 $
b0 %
b11100000000000000000001 &
0'
b1001010001101100110110110100111 (
b1010000000100001000111010100011 )
b101 *
b0 +

#325000
1'

#330000
b1100010111000000000000011100101 "
b10101001000010011111001010110101 #
b10 $
b1011111010011111001110011010 %
b0 &
0'
b1100010111000000000000011100101 (
b10101001000010011111001010110101 )
b10 *
b1011111010011111001110011010 +

#335000
1'

#340000
b10101110010011000110101101000110 "
b1110011010000000110000001011100 #
b101 $
b0 %
b1011111010011111001110011010 &
0'
b10101110010011000110101101000110 (
b1110011010000000110000001011100 )
b101 *
b0 +

#345000
1'

#350000
b10100001100100100010111100111011 "
b1010110001000000110000101000001 #
b10 $
b11110111101100101001000001111100 %
b0 &
0'
b10100001100100100010111100111011 (
b1010110001000000110000101000001 )
b10 *
b11110111101100101001000001111100 +

#355000
1'

#360000
b10111011010010011111101101110101 "
b100011011001100110010000111 #
b110 $
b10110110110111010010111011101110 %
b11110111101100101001000001111100 &
0'
b10111011010010011111101101110101 (
b100011011001100110010000111 )
b110 *
b10110110110111010010111011101110 +

#365000
1'

#370000
b100101000100100101011001010010 "
b100101111111101111101111000010 #
b0 $
b100101000100100101001001000010 %
b10110110110111010010111011101110 &
0'
b100101000100100101011001010010 (
b100101111111101111101111000010 )
b0 *
b100101000100100101001001000010 +

#375000
1'

#380000
b10110111111001001010001111100101 "
b1100001010010001111011100110111 #
b111 $
b0 %
b100101000100100101001001000010 &
0'
b10110111111001001010001111100101 (
b1100001010010001111011100110111 )
b111 *
b0 +

#385000
1'

#390000
b111101111101110101000111010011 "
b10000110010110110100110110001010 #
b10 $
b11000100010100101001111101011101 %
b0 &
0'
b111101111101110101000111010011 (
b10000110010110110100110110001010 )
b10 *
b11000100010100101001111101011101 +

#395000
1'

#400000
b11010001010100110000100000011 "
b10111110001111111111000101101111 #
b1 $
b10111110001111111111000101101111 %
b11000100010100101001111101011101 &
0'
b11010001010100110000100000011 (
b10111110001111111111000101101111 )
b1 *
b10111110001111111111000101101111 +

#405000
1'

#410000
b1111010110010100011110010111011 "
b1111100001101110100001101000010 #
b11 $
b0 %
b10111110001111111111000101101111 &
0'
b1111010110010100011110010111011 (
b1111100001101110100001101000010 )
b11 *
b0 +

#415000
1'

#420000
b10000001011010010001010000110101 "
b10010110011000011010010001000110 #
b10 $
b10111110010101011100001111011 %
b0 &
0'
b10000001011010010001010000110101 (
b10010110011000011010010001000110 )
b10 *
b10111110010101011100001111011 +

#425000
1'

#430000
b1101001010100001110001011100110 "
b10010001001010111110000100000001 #
b101 $
b0 %
b10111110010101011100001111011 &
0'
b1101001010100001110001011100110 (
b10010001001010111110000100000001 )
b101 *
b0 +

#435000
1'

#440000
b1010111100100111111111100100010 "
b10010010100101001111010100110110 #
b11 $
b0 &
0'
b1010111100100111111111100100010 (
b10010010100101001111010100110110 )
b11 *

#445000
1'

#450000
b100000101110000110011001100 "
b1111011111001011101100000011100 #
b100 $
0'
b100000101110000110011001100 (
b1111011111001011101100000011100 )
b100 *

#455000
1'

#460000
b101100110100010101110110111001 "
b1010011011110011101011100111110 #
b10 $
b10000000010010110011010011110111 %
0'
b101100110100010101110110111001 (
b1010011011110011101011100111110 )
b10 *
b10000000010010110011010011110111 +

#465000
1'

#470000
b1101011111011010101001011101100 "
b1010111100100001110010000001011 #
b110 $
b10100010111000110111011100001 %
b10000000010010110011010011110111 &
0'
b1101011111011010101001011101100 (
b1010111100100001110010000001011 )
b110 *
b10100010111000110111011100001 +

#475000
1'

#480000
b111100001101010010100100100000 "
b100011000100100000111000100 #
b101 $
b0 %
b10100010111000110111011100001 &
0'
b111100001101010010100100100000 (
b100011000100100000111000100 )
b101 *
b0 +

#485000
1'

#490000
b11111000100011111010010001010 "
b1110000010011111001010010110001 #
b0 $
b10000000000011001010010000000 %
b0 &
0'
b11111000100011111010010001010 (
b1110000010011111001010010110001 )
b0 *
b10000000000011001010010000000 +

#495000
1'

#500000
b1111101110101001001100000010001 "
b101100100001001011110111010001 #
b100 $
b0 %
b10000000000011001010010000000 &
0'
b1111101110101001001100000010001 (
b101100100001001011110111010001 )
b100 *
b0 +

#505000
1'

#510000
b10110000000100010001001011010110 "
b1001011100101101011001001011100 #
b101 $
b0 &
0'
b10110000000100010001001011010110 (
b1001011100101101011001001011100 )
b101 *

#515000
1'

#520000
b10111001110111100111000110100110 "
b1001001011010110100101001101101 #
b111 $
0'
b10111001110111100111000110100110 (
b1001001011010110100101001101101 )
b111 *

#525000
1'

#530000
b1001000000011100001001000111010 "
b1111001011111000101110101000011 #
b11 $
0'
b1001000000011100001001000111010 (
b1111001011111000101110101000011 )
b11 *

#535000
1'

#540000
b1000110100011010100011110000000 "
b10110011010110101100111011101001 #
b0 $
b10000010000100011010000000 %
0'
b1000110100011010100011110000000 (
b10110011010110101100111011101001 )
b0 *
b10000010000100011010000000 +

#545000
1'

#550000
b1110001100100010011101010010111 "
b1111011011010001110000100100011 #
b11 $
b0 %
b10000010000100011010000000 &
0'
b1110001100100010011101010010111 (
b1111011011010001110000100100011 )
b11 *
b0 +

#555000
1'

#560000
b1101000001010111110000000001010 "
b1000001111101100010100010100011 #
b100 $
b0 &
0'
b1101000001010111110000000001010 (
b1000001111101100010100010100011 )
b100 *

#565000
1'

#570000
b10101000001100011100111111101010 "
b110011100001110110001100111010 #
b111 $
0'
b10101000001100011100111111101010 (
b110011100001110110001100111010 )
b111 *

#575000
1'

#580000
b1100001101101000001110100001101 "
b11011101100110100001101000100 #
b11 $
0'
b1100001101101000001110100001101 (
b11011101100110100001101000100 )
b11 *

#585000
1'

#590000
b1001110100100010011100100011001 "
b1000011111001010001001100101110 #
b101 $
0'
b1001110100100010011100100011001 (
b1000011111001010001001100101110 )
b101 *

#595000
1'

#600000
b110110110101110011011001001000 "
b100101100110010011000000111011 #
b10 $
b1011100011100000110011010000011 %
0'
b110110110101110011011001001000 (
b100101100110010011000000111011 )
b10 *
b1011100011100000110011010000011 +

#605000
1'

#610000
b1100001000100110101110000011011 "
b1110100001010100110100101010100 #
b0 $
b1100000000000100100100000010000 %
b1011100011100000110011010000011 &
0'
b1100001000100110101110000011011 (
b1110100001010100110100101010100 )
b0 *
b1100000000000100100100000010000 +

#615000
1'

#620000
b10111110110101101110010100101001 "
b10101011000000011001111110011101 #
b100 $
b0 %
b1100000000000100100100000010000 &
0'
b10111110110101101110010100101001 (
b10101011000000011001111110011101 )
b100 *
b0 +

#625000
1'

#630000
b10111000010011011011000101111011 "
b1100000101001111101110111000 #
b0 $
b1000000001001011000100111000 %
b0 &
0'
b10111000010011011011000101111011 (
b1100000101001111101110111000 )
b0 *
b1000000001001011000100111000 +

#635000
1'

#640000
b1110101101010011001000011111011 "
b1001010111010111110000011100001 #
b101 $
b0 %
b1000000001001011000100111000 &
0'
b1110101101010011001000011111011 (
b1001010111010111110000011100001 )
b101 *
b0 +

#645000
1'

#650000
b1011000100111101010000010110111 "
b11001110011001001001011100 #
b110 $
b1010101011001010000111001011011 %
b0 &
0'
b1011000100111101010000010110111 (
b11001110011001001001011100 )
b110 *
b1010101011001010000111001011011 +

#655000
1'

#660000
b10101111101111100001100111001000 "
b1111000111000110010001101011000 #
b111 $
b0 %
b1010101011001010000111001011011 &
0'
b10101111101111100001100111001000 (
b1111000111000110010001101011000 )
b111 *
b0 +

#665000
1'

#670000
b110001110111110011001001110101 "
b1010001100000011100010000001111 #
b100 $
b0 &
0'
b110001110111110011001001110101 (
b1010001100000011100010000001111 )
b100 *

#675000
1'

#680000
b1000000000101010100011011011011 "
b1001111111101110111010111 #
0'
b1000000000101010100011011011011 (
b1001111111101110111010111 )

#685000
1'

#690000
b10011001001101110011110000100011 "
b10110011000111110001000001001101 #
b11 $
0'
b10011001001101110011110000100011 (
b10110011000111110001000001001101 )
b11 *

#695000
1'

#700000
b1110101100100101100001111000111 "
b1110011001101000101011100101000 #
0'
b1110101100100101100001111000111 (
b1110011001101000101011100101000 )

#705000
1'

#710000
b1001010110100010110111011000011 "
b1100011010111001001101001011 #
b0 $
b1000010000010000001001000011 %
0'
b1001010110100010110111011000011 (
b1100011010111001001101001011 )
b0 *
b1000010000010000001001000011 +

#715000
1'

#720000
b1110001100100011101110111001110 "
b1111111100101011100010010 #
b1100100000101010100000010 %
b1000010000010000001001000011 &
0'
b1110001100100011101110111001110 (
b1111111100101011100010010 )
b1100100000101010100000010 +

#725000
1'

#730000
b11001100100100010101010110001 "
b1001100110011111100010111010101 #
b100 $
b0 %
b1100100000101010100000010 &
0'
b11001100100100010101010110001 (
b1001100110011111100010111010101 )
b100 *
b0 +

#735000
1'

#740000
b1110100101100011000011111100001 "
b10111110011000011010001110100100 #
b110 $
b10110110010011111110010000111101 %
b0 &
0'
b1110100101100011000011111100001 (
b10111110011000011010001110100100 )
b110 *
b10110110010011111110010000111101 +

#745000
1'

#750000
b1000011000001010011110000111010 "
b1010111111100111100111001010101 #
b100 $
b0 %
b10110110010011111110010000111101 &
0'
b1000011000001010011110000111010 (
b1010111111100111100111001010101 )
b100 *
b0 +

#755000
1'

#760000
b10011101110001001000001111011110 "
b1001100101001010101011000110111 #
b0 $
b1100100001000000001000010110 %
b0 &
0'
b10011101110001001000001111011110 (
b1001100101001010101011000110111 )
b0 *
b1100100001000000001000010110 +

#765000
1'

#770000
b1111010100000100010001010010100 "
b10001111101010101001001001110001 #
b101 $
b0 %
b1100100001000000001000010110 &
0'
b1111010100000100010001010010100 (
b10001111101010101001001001110001 )
b101 *
b0 +

#775000
1'

#780000
b100100000011111000011100100000 "
b10101101011011110001011001001111 #
b100 $
b0 &
0'
b100100000011111000011100100000 (
b10101101011011110001011001001111 )
b100 *

#785000
1'

#790000
b1011111111101000111101010000 "
b100111111100010011100011100011 #
b101 $
0'
b1011111111101000111101010000 (
b100111111100010011100011100011 )
b101 *

#795000
1'

#800000
b1001011111000010110010111010110 "
b1001100000000001100000000000100 #
b100 $
0'
b1001011111000010110010111010110 (
b1001100000000001100000000000100 )
b100 *

#805000
1'

#810000
b1011000011010011001001010010010 "
b1010111111111110100111101010100 #
b0 $
b1010000011010010000001000010000 %
0'
b1011000011010011001001010010010 (
b1010111111111110100111101010100 )
b0 *
b1010000011010010000001000010000 +

#815000
1'

#820000
b1110100100111000101000111000000 "
b100011111000001011010100101010 #
b100 $
b0 %
b1010000011010010000001000010000 &
0'
b1110100100111000101000111000000 (
b100011111000001011010100101010 )
b100 *
b0 +

#825000
1'

#830000
b111110001111100010011100111100 "
b1111100010010100100011110111101 #
b0 $
b111100000010100000011100111100 %
b0 &
0'
b111110001111100010011100111100 (
b1111100010010100100011110111101 )
b0 *
b111100000010100000011100111100 +

#835000
1'

#840000
b101111110100010011010110011100 "
b1110000111001101001100101111101 #
b11 $
b0 %
b111100000010100000011100111100 &
0'
b101111110100010011010110011100 (
b1110000111001101001100101111101 )
b11 *
b0 +

#845000
1'

#850000
b1101101011001010000010000000000 "
b101111001001001100000010111001 #
b0 $
b101101001001000000000000000000 %
b0 &
0'
b1101101011001010000010000000000 (
b101111001001001100000010111001 )
b0 *
b101101001001000000000000000000 +

#855000
1'

#860000
b10000010111110000010000110111001 "
b1011110111101011111011001010110 #
b101 $
b0 %
b101101001001000000000000000000 &
0'
b10000010111110000010000110111001 (
b1011110111101011111011001010110 )
b101 *
b0 +

#865000
1'

#870000
b10111100011010111111010010011100 "
b1001100010110101111101001010110 #
b110 $
b1110000000100001111101001000110 %
b0 &
0'
b10111100011010111111010010011100 (
b1001100010110101111101001010110 )
b110 *
b1110000000100001111101001000110 +

#875000
1'

#880000
b1110010001010100000111100111100 "
b1001111010100110001110000001111 #
b100 $
b0 %
b1110000000100001111101001000110 &
0'
b1110010001010100000111100111100 (
b1001111010100110001110000001111 )
b100 *
b0 +

#885000
1'

#890000
b10011000110011101100001101011001 "
b1011101111110001000010101011 #
b11 $
b0 &
0'
b10011000110011101100001101011001 (
b1011101111110001000010101011 )
b11 *

#895000
1'

#900000
b1101110100110000011100000101111 "
b1111101111010010001111111100111 #
b10 $
b11101100100000010101100000010110 %
0'
b1101110100110000011100000101111 (
b1111101111010010001111111100111 )
b10 *
b11101100100000010101100000010110 +

#905000
1'

#910000
b10100011010101111010001101011100 "
b10110101101111110001101000000 #
b110 $
b10001100100111111100000000011100 %
b11101100100000010101100000010110 &
0'
b10100011010101111010001101011100 (
b10110101101111110001101000000 )
b110 *
b10001100100111111100000000011100 +

#915000
1'

#920000
b10100100011100100000100011011111 "
b10000101010100000001101101110000 #
b101 $
b0 %
b10001100100111111100000000011100 &
0'
b10100100011100100000100011011111 (
b10000101010100000001101101110000 )
b101 *
b0 +

#925000
1'

#930000
b1110100110111111000101001110001 "
b10101000101001111011111011001100 #
b110 $
b11001100001101111100101110100101 %
b0 &
0'
b1110100110111111000101001110001 (
b10101000101001111011111011001100 )
b110 *
b11001100001101111100101110100101 +

#935000
1'

#940000
b1010001000011000001110010101111 "
b1001101000110011100011110101011 #
b11111100100101010100000100 %
b11001100001101111100101110100101 &
0'
b1010001000011000001110010101111 (
b1001101000110011100011110101011 )
b11111100100101010100000100 +

#945000
1'

#950000
b10101011001000011100111011010101 "
b1000001111110010101001000011100 #
b10 $
b11101101000110110010000011110001 %
b11111100100101010100000100 &
0'
b10101011001000011100111011010101 (
b1000001111110010101001000011100 )
b10 *
b11101101000110110010000011110001 +

#955000
1'

#960000
b10011011111011110110010000111011 "
b10010011000001010110111011001100 #
b101 $
b0 %
b11101101000110110010000011110001 &
0'
b10011011111011110110010000111011 (
b10010011000001010110111011001100 )
b101 *
b0 +

#965000
1'

#970000
b10010010000011010001010100010001 "
b10111110001001110011110110100001 #
b1 $
b10111110001011110011110110110001 %
b0 &
0'
b10010010000011010001010100010001 (
b10111110001001110011110110100001 )
b1 *
b10111110001011110011110110110001 +

#975000
1'

#980000
b10110000110100101000010010110011 "
b1011010000101101010000111011100 #
b101 $
b0 %
b10111110001011110011110110110001 &
0'
b10110000110100101000010010110011 (
b1011010000101101010000111011100 )
b101 *
b0 +

#985000
1'

#990000
b10011100101100011011110000000000 "
b1101100001000111011011011101101 #
b110 $
b110000100011100000010100010011 %
b0 &
0'
b10011100101100011011110000000000 (
b1101100001000111011011011101101 )
b110 *
b110000100011100000010100010011 +

#995000
1'

#1000000
b1001010100010100100010101101001 "
b10011100111101100011101110100000 #
b10 $
b11100111100000001000000100001001 %
b110000100011100000010100010011 &
0'
b1001010100010100100010101101001 (
b10011100111101100011101110100000 )
b10 *
b11100111100000001000000100001001 +

#1005000
1'

#1010000
b10001011011010000011110110011111 "
b10111001101001111111011110100000 #
b111 $
b1 %
b11100111100000001000000100001001 &
0'
b10001011011010000011110110011111 (
b10111001101001111111011110100000 )
b111 *
b1 +

#1015000
1'

#1020000
b1 &
