hw1/src/alu.v
// alu.v

module alu 
#(parameter DATA_WIDTH = 32)
(
    input wire [DATA_WIDTH-1:0] A, B,
    input wire [2:0] ALUOp,
    output reg [DATA_WIDTH-1:0] Q
    // output reg Cout
    // carry-out is not part of the specification!
);

always @(*)
begin
    case (ALUOp)
        3'b000: Q = A & B; // logical and
        3'b001: Q = A | B; // logical or
        3'b010: Q = A + B; // addition
        3'b110: Q = A - B; // subtraction
        3'b111: begin // set if A less than B
            if (A < B) begin
                // Q = 1; 
                Q = { { (DATA_WIDTH-1){1'b0} }, 1'b1 };
            end else begin
                // Q = 0;
                Q = { { (DATA_WIDTH-1){1'b0} }, 1'b0 };
            end
        end
        default:
            // Q = 0; 
            Q = { (DATA_WIDTH){1'b0} };
    endcase
end

endmodule

hw1/verif/tb_alu.sv
// tb_alu.sv
//
// https://www.asic-world.com/systemverilog/system_task_function4.html

module tb_alu;

    localparam DATA_WIDTH = 32;

    // inputs
    reg [DATA_WIDTH-1:0] A, B;
    reg [2:0] ALUOp;

    // outputs
    wire [DATA_WIDTH-1:0] Q;
    // wire Cout;

    // instantiation unit under test 
    alu #(.DATA_WIDTH(DATA_WIDTH)) dut (
        .A(A),
        .B(B),
        .ALUOp(ALUOp),
        .Q(Q)
        // .Cout(Cout)
    );

    reg [DATA_WIDTH-1:0] exp;
    reg clk;
    always #5 clk = ~clk;

    initial begin
        $dumpfile("waveform.vcd");
        $dumpvars;

        clk = 0;
        exp = { (DATA_WIDTH){1'bx} };

        A = 32'd1;
        B = 32'd2;
        exp = 3;
        ALUOp = 3'b010;
        #10;
        $display("A = %h, B = %h, ALUOp = %b", A, B, ALUOp);
        assert(Q == exp) $display("SUCCESS! Expected: %h. Actual: %h", Q, exp);
        else $error("FAILED! Expected: %h. Actual: %h", Q, exp);
        $display();


        A = 32'd3;
        B = 32'd4;
        exp = -1;
        ALUOp = 3'b110;
        #10;
        $display("A = %h, B = %h, ALUOp = %b", A, B, ALUOp);
        assert(Q == exp) $display("SUCCESS! Expected: %h. Actual: %h", Q, exp);
        else $error("FAILED! Expected: %h. Actual: %h", Q, exp);
        $display();

        // Apply stimulus for 10 clock cycles;
        repeat (10) begin
            #10; // Wait for rising edge clock 

            $display("A = %h, B = %h, ALUOp = %b", A, B, ALUOp);
            case (ALUOp)
                3'b000: begin
                    exp = A & B;
                    assert(Q == exp) $display("SUCCESS! Expected: %h. Actual: %h", Q, exp);
                    else $error("FAILED! Expected: %h. Actual: %h", Q, exp);
                end
                3'b001: begin
                    exp = A | B;
                    assert(Q == exp) $display("SUCCESS! Expected: %h. Actual: %h", Q, exp);
                    else $error("FAILED! Expected: %h. Actual: %h", Q, exp);
                end
                3'b010: begin
                    exp = A + B;
                    assert(Q == exp) $display("SUCCESS! Expected: %h. Actual: %h", Q, exp);
                    else $error("FAILED! Expected: %h. Actual: %h", Q, exp);
                end
                3'b110: begin
                    exp = A - B;
                    assert(Q == exp) $display("SUCCESS! Expected: %h. Actual: %h", Q, exp);
                    else $error("FAILED! Expected: %h. Actual: %h", Q, exp);
                end
                3'b111: begin
                    if (A < B) begin
                        exp = { { (DATA_WIDTH-1){1'b0} }, 1'b1}; // exp = 1
                    end else begin
                        exp = { (DATA_WIDTH){1'b0} }; // exp = 0
                    end
                    assert(Q == exp) $display("SUCCESS! Expected: %h. Actual: %h", Q, exp);
                    else $error("FAILED! Expected: %h. Actual: %h", Q, exp);
                end
                default: begin
                    exp = 0;
                    assert(Q == exp) $display("SUCCESS! Expected: %h. Actual: %h", Q, exp);
                    else $error("FAILED! Expected: %h. Actual: %h", Q, exp);
                end
            endcase

            $display();

            A = A + 1;
            B = B + 1;
            ALUOp = ALUOp + 1;
        end // repeat

        $finish;
    end // initial
endmodule

hw1/run/waveform.vcd
$date
   Fri Oct 11 17:48:32 2024
$end

$version
  2023.2.2
  $dumpfile ("waveform.vcd") 
$end

$timescale
  1ps
$end

$scope module tb_alu $end
$var reg 32 ! A [31:0] $end
$var reg 32 " B [31:0] $end
$var reg 3 # ALUOp [2:0] $end
$var wire 32 $ Q [31:0] $end
$var reg 32 % exp [31:0] $end
$var reg 1 & clk $end
$scope module dut $end
$var wire 32 ' A [31:0] $end
$var wire 32 ( B [31:0] $end
$var wire 3 ) ALUOp [2:0] $end
$var reg 32 * Q [31:0] $end
$upscope $end
$upscope $end
$enddefinitions $end

#0
$dumpvars
b1 !
b10 "
b10 #
b11 $
b11 %
0&
b1 '
b10 (
b10 )
b11 *
$end

#5000
1&

#10000
b11 !
b100 "
b110 #
b11111111111111111111111111111111 $
b11111111111111111111111111111111 %
0&
b11 '
b100 (
b110 )
b11111111111111111111111111111111 *

#15000
1&

#20000
0&

#25000
1&

#30000
b100 !
b101 "
b111 #
b1 $
0&
b100 '
b101 (
b111 )
b1 *

#35000
1&

#40000
b101 !
b110 "
b0 #
b100 $
b1 %
0&
b101 '
b110 (
b0 )
b100 *

#45000
1&

#50000
b110 !
b111 "
b1 #
b111 $
b100 %
0&
b110 '
b111 (
b1 )
b111 *

#55000
1&

#60000
b111 !
b1000 "
b10 #
b1111 $
b111 %
0&
b111 '
b1000 (
b10 )
b1111 *

#65000
1&

#70000
b1000 !
b1001 "
b11 #
b0 $
b1111 %
0&
b1000 '
b1001 (
b11 )
b0 *

#75000
1&

#80000
b1001 !
b1010 "
b100 #
b0 %
0&
b1001 '
b1010 (
b100 )

#85000
1&

#90000
b1010 !
b1011 "
b101 #
0&
b1010 '
b1011 (
b101 )

#95000
1&

#100000
b1011 !
b1100 "
b110 #
b11111111111111111111111111111111 $
0&
b1011 '
b1100 (
b110 )
b11111111111111111111111111111111 *

#105000
1&

#110000
b1100 !
b1101 "
b111 #
b1 $
b11111111111111111111111111111111 %
0&
b1100 '
b1101 (
b111 )
b1 *

#115000
1&

#120000
b1101 !
b1110 "
b0 #
b1 %
