hw4/src/mac.v
module mac
#(
    parameter DATA_WIDTH = 16
)(
    input wire i_clk,
    input wire i_rst,
    input wire i_en,
    input wire [DATA_WIDTH-1:0] iv_a,
    input wire [DATA_WIDTH-1:0] iv_b,
    output wire [DATA_WIDTH-1:0] ov_c
);

    reg [DATA_WIDTH*2-1:0] sum_full;
    assign ov_c = sum_full[DATA_WIDTH-1:0];

    always @(posedge i_clk) begin
        if (i_rst) begin
            sum_full <= 0;
        end else if (i_en) begin
            sum_full <= sum_full + iv_a * iv_b;
        end
    end

endmodule

hw4/src/single_port_ram.v
module single_port_ram
#(
    parameter DATA_WIDTH = 24,
    parameter ADDR_WIDTH = 8
)(
    input wire i_clk,
    input wire i_rst,
    input wire i_en,
    input wire i_we,
    input wire [ADDR_WIDTH-1:0] iv_addr,
    input wire [DATA_WIDTH-1:0] iv_din,
    output reg [DATA_WIDTH-1:0] ov_dout
);
    reg [DATA_WIDTH-1:0] RAM [2**ADDR_WIDTH-1:0];

    initial begin
        RAM[0] = 16'h00A0;
        RAM[1] = 16'h00B1;
        RAM[2] = 16'h00C2;
        RAM[3] = 16'h00D3;
        RAM[4] = 16'h00E4;
        RAM[5] = 16'h00F5;
        RAM[6] = 16'h0006;
        RAM[7] = 16'h0017;
    end

    always @(posedge i_clk) begin
        if (i_rst) begin // reset output register
            ov_dout <= 0;
        end else if(i_en) begin
            if (i_we) begin // write
                RAM[iv_addr] <= iv_din;
                ov_dout <= iv_din;
            end else begin // read
                ov_dout <= RAM[iv_addr];
            end
        end
    end

endmodule

hw4/src/memory_modelling.v
module memory_modelling
#(
    parameter DATA_WIDTH = 16,
    parameter RAM_DEPTH = 8
)(
    input wire i_clk,
    input wire i_rst,
    input wire i_en,
    input wire [DATA_WIDTH-1:0] iv_b,
    output wire [DATA_WIDTH-1:0] ov_sum
);

    localparam ADDR_WIDTH = $clog2(RAM_DEPTH);
    reg [ADDR_WIDTH-1:0] ram_addr;
    wire [DATA_WIDTH-1:0] ram_din;
    wire [DATA_WIDTH-1:0] ram_dout;

    single_port_ram
    #(
        .DATA_WIDTH(DATA_WIDTH),
        .ADDR_WIDTH(ADDR_WIDTH)
    ) spram_inst (
        .i_clk(i_clk),
        .i_rst(i_rst),
        .i_en(i_en),
        .i_we(0),
        .iv_addr(ram_addr),
        .iv_din(ram_din),
        .ov_dout(ram_dout)
    );

    wire [DATA_WIDTH-1:0] sum;
    assign ov_sum = sum;

    mac
    #(
        .DATA_WIDTH(DATA_WIDTH)
    ) mac_inst (
        .i_clk(i_clk),
        .i_rst(i_rst),
        .i_en(i_en),
        .iv_a(ram_dout),
        .iv_b(iv_b),
        .ov_c(sum)
    );

    always @(posedge i_clk) begin
        if (i_rst) begin
            ram_addr <= 0;
        end else if (i_en) begin
            ram_addr <= ram_addr + 1;
        end
    end

endmodule

hw4/src/top_level.v
module top_level
#(
    parameter DATA_WIDTH = 16,
    parameter RAM_DEPTH = 8
)(
    input wire i_clk,
    input wire i_rst,
    input wire i_en,
    input wire [DATA_WIDTH-1:0] iv_b,
    output wire [DATA_WIDTH-1:0] ov_sum
);

    memory_modelling
    #(
        .DATA_WIDTH(DATA_WIDTH),
        .RAM_DEPTH(RAM_DEPTH)
    ) memory_modelling_inst (
        .i_clk(i_clk),
        .i_rst(i_rst),
        .i_en(i_en),
        .iv_b(iv_b),
        .ov_sum(ov_sum)
    );

endmodule

hw4/verif/tb_memory_modelling.sv

module tb_memory_modelling;

    localparam DATA_WIDTH = 16;
    localparam RAM_DEPTH = 8;
    reg tb_clk;
    reg tb_rst;
    reg tb_en;
    reg [DATA_WIDTH-1:0] tb_a [RAM_DEPTH-1:0];
    reg [DATA_WIDTH-1:0] tb_b;

    wire [DATA_WIDTH-1:0] dut_sum;

    int num_errors = 0;
    reg [DATA_WIDTH:0] tb_exp_sum;

    top_level
    #(
        .DATA_WIDTH(DATA_WIDTH),
        .RAM_DEPTH(RAM_DEPTH)
    ) top_level_inst (

        .i_clk(tb_clk),
        .i_rst(tb_rst),
        .i_en(tb_en),
        .iv_b(tb_b),
        .ov_sum(dut_sum)
    );

    task assert_and_report(input [DATA_WIDTH-1:0] expected, input [DATA_WIDTH-1:0] actual);
    begin
        if (actual == expected) begin
            $display(" SUCCESS!\n  Expected: %b\n  Actual:   %b", expected, actual);
        end else begin
            $display(" FAILURE!\n  Expected: %b\n  Actual:   %b", expected, actual);
            num_errors = num_errors + 1;
        end
    end
    endtask // assert_and_report

    always_comb begin
        tb_exp_sum = '0;
        for (int i = 0; i < RAM_DEPTH; i = i + 1) begin
            tb_exp_sum += tb_b * tb_a[i];
        end
    end

    always #5 tb_clk = ~tb_clk;
    initial begin
        $dumpfile("waveform.vcd");
        $dumpvars;

        tb_a[0] = 16'h00A0;
        tb_a[1] = 16'h00B1;
        tb_a[2] = 16'h00C2;
        tb_a[3] = 16'h00D3;
        tb_a[4] = 16'h00E4;
        tb_a[5] = 16'h00F5;
        tb_a[6] = 16'h0006;
        tb_a[7] = 16'h0017;

        num_errors = 0;
        tb_clk = 1;
        tb_rst = 1;
        tb_en = 0;

        @(posedge tb_clk);
        tb_rst = 0;
        tb_en = 0;
        @(posedge tb_clk);

        repeat (100) begin
            tb_b = $urandom() & 4'b1111;
            repeat(8) begin
                tb_rst = 0;
                tb_en = 1;
                @(posedge tb_clk);
            end
            tb_en = 0;
            assert_and_report(tb_exp_sum, dut_sum);
            @(posedge tb_clk);
            tb_rst = 1;
            $display();
            repeat (20) begin
                @(posedge tb_clk);
            end
        end

        $display();
        $display("Total number of errors: %d", num_errors);
        $display();

        $finish;
    end // initial


    initial begin
        #1ms;
        $display("Simulation terminated after 1 millisecond.");
        $finish;
    end // initial
endmodule

hw4/sim/waveform.vcd
$date
   Sat Dec 14 19:29:44 2024
$end

$version
  2023.2.2
  $dumpfile ("waveform.vcd") 
$end

$timescale
  1ns
$end

$scope module tb_memory_modelling $end
$var reg 1 ! tb_clk $end
$var reg 1 " tb_rst $end
$var reg 1 # tb_en $end
$var reg 16 $ tb_b [15:0] $end
$var wire 16 % dut_sum [15:0] $end
$var reg 32 & num_errors [31:0] $end
$var reg 17 ' tb_exp_sum [16:0] $end
$scope module top_level_inst $end
$var wire 1 ( i_clk $end
$var wire 1 ) i_rst $end
$var wire 1 * i_en $end
$var wire 16 + iv_b [15:0] $end
$var wire 16 % ov_sum [15:0] $end
$scope module memory_modelling_inst $end
$var wire 1 ( i_clk $end
$var wire 1 ) i_rst $end
$var wire 1 * i_en $end
$var wire 16 + iv_b [15:0] $end
$var wire 16 % ov_sum [15:0] $end
$var reg 3 , ram_addr [2:0] $end
$var wire 16 - ram_din [15:0] $end
$var wire 16 . ram_dout [15:0] $end
$var wire 16 / sum [15:0] $end
$scope module spram_inst $end
$var wire 1 ( i_clk $end
$var wire 1 ) i_rst $end
$var wire 1 * i_en $end
$var wire 1 0 i_we $end
$var wire 3 1 iv_addr [2:0] $end
$var wire 16 - iv_din [15:0] $end
$var reg 16 2 ov_dout [15:0] $end
$upscope $end
$scope module mac_inst $end
$var wire 1 ( i_clk $end
$var wire 1 ) i_rst $end
$var wire 1 * i_en $end
$var wire 16 . iv_a [15:0] $end
$var wire 16 + iv_b [15:0] $end
$var wire 16 / ov_c [15:0] $end
$var reg 32 3 sum_full [31:0] $end
$upscope $end
$upscope $end
$upscope $end
$scope begin Block43_5 $end
$var reg 32 4 i [31:0] $end
$upscope $end
$scope task assert_and_report $end
$var reg 16 5 expected [15:0] $end
$var reg 16 6 actual [15:0] $end
$upscope $end
$upscope $end
$enddefinitions $end

#0
$dumpvars
1!
1"
0#
bx $
b0 %
b0 &
bx '
1(
1)
0*
bx +
b0 ,
bz -
b0 .
b0 /
00
b0 1
b0 2
b0 3
b1000 4
bx 5
bx 6
$end

#50
0!
0(

#100
1!
0"
1(
0)

#150
0!
0(

#200
1!
1#
b0 $
b0 '
1(
1*
b0 +
b1 ,
b10100000 .
b1 1
b10100000 2
b1000 4

#250
0!
0(

#300
1!
1(
b10 ,
b10110001 .
b10 1
b10110001 2

#350
0!
0(

#400
1!
1(
b11 ,
b11000010 .
b11 1
b11000010 2

#450
0!
0(

#500
1!
1(
b100 ,
b11010011 .
b100 1
b11010011 2

#550
0!
0(

#600
1!
1(
b101 ,
b11100100 .
b101 1
b11100100 2

#650
0!
0(

#700
1!
1(
b110 ,
b11110101 .
b110 1
b11110101 2

#750
0!
0(

#800
1!
1(
b111 ,
b110 .
b111 1
b110 2

#850
0!
0(

#900
1!
1(
b0 ,
b10111 .
b0 1
b10111 2

#950
0!
0(

#1000
1!
0#
1(
0*
b0 5
b0 6

#1050
0!
0(

#1100
1!
1"
1(
1)
b0 .
b0 2

#1150
0!
0(

#1200
1!
1(

#1250
0!
0(

#1300
1!
1(

#1350
0!
0(

#1400
1!
1(

#1450
0!
0(

#1500
1!
1(

#1550
0!
0(

#1600
1!
1(

#1650
0!
0(

#1700
1!
1(

#1750
0!
0(

#1800
1!
1(

#1850
0!
0(

#1900
1!
1(

#1950
0!
0(

#2000
1!
1(

#2050
0!
0(

#2100
1!
1(

#2150
0!
0(

#2200
1!
1(

#2250
0!
0(

#2300
1!
1(

#2350
0!
0(

#2400
1!
1(

#2450
0!
0(

#2500
1!
1(

#2550
0!
0(

#2600
1!
1(

#2650
0!
0(

#2700
1!
1(

#2750
0!
0(

#2800
1!
1(

#2850
0!
0(

#2900
1!
1(

#2950
0!
0(

#3000
1!
1(

#3050
0!
0(

#3100
1!
0"
1#
b1010 $
b11000010011000 '
1(
0)
1*
b1010 +
b1 ,
b10100000 .
b1 1
b10100000 2
b1000 4

#3150
0!
0(

#3200
1!
b11001000000 %
1(
b10 ,
b10110001 .
b11001000000 /
b10 1
b10110001 2
b11001000000 3

#3250
0!
0(

#3300
1!
b110100101010 %
1(
b11 ,
b11000010 .
b110100101010 /
b11 1
b11000010 2
b110100101010 3

#3350
0!
0(

#3400
1!
b1010010111110 %
1(
b100 ,
b11010011 .
b1010010111110 /
b100 1
b11010011 2
b1010010111110 3

#3450
0!
0(

#3500
1!
b1110011111100 %
1(
b101 ,
b11100100 .
b1110011111100 /
b101 1
b11100100 2
b1110011111100 3

#3550
0!
0(

#3600
1!
b10010111100100 %
1(
b110 ,
b11110101 .
b10010111100100 /
b110 1
b11110101 2
b10010111100100 3

#3650
0!
0(

#3700
1!
b10111101110110 %
1(
b111 ,
b110 .
b10111101110110 /
b111 1
b110 2
b10111101110110 3

#3750
0!
0(

#3800
1!
b10111110110010 %
1(
b0 ,
b10111 .
b10111110110010 /
b0 1
b10111 2
b10111110110010 3

#3850
0!
0(

#3900
1!
0#
b1 &
1(
0*
b11000010011000 5
b10111110110010 6

#3950
0!
0(

#4000
1!
1"
b0 %
1(
1)
b0 .
b0 /
b0 2
b0 3

#4050
0!
0(

#4100
1!
1(

#4150
0!
0(

#4200
1!
1(

#4250
0!
0(

#4300
1!
1(

#4350
0!
0(

#4400
1!
1(

#4450
0!
0(

#4500
1!
1(

#4550
0!
0(

#4600
1!
1(

#4650
0!
0(

#4700
1!
1(

#4750
0!
0(

#4800
1!
1(

#4850
0!
0(

#4900
1!
1(

#4950
0!
0(

#5000
1!
1(

#5050
0!
0(

#5100
1!
1(

#5150
0!
0(

#5200
1!
1(

#5250
0!
0(

#5300
1!
1(

#5350
0!
0(

#5400
1!
1(

#5450
0!
0(

#5500
1!
1(

#5550
0!
0(

#5600
1!
1(

#5650
0!
0(

#5700
1!
1(

#5750
0!
0(

#5800
1!
1(

#5850
0!
0(

#5900
1!
1(

#5950
0!
0(

#6000
1!
0"
1#
b1000 $
b10011011100000 '
1(
0)
1*
b1000 +
b1 ,
b10100000 .
b1 1
b10100000 2
b1000 4

#6050
0!
0(

#6100
1!
b10100000000 %
1(
b10 ,
b10110001 .
b10100000000 /
b10 1
b10110001 2
b10100000000 3

#6150
0!
0(

#6200
1!
b101010001000 %
1(
b11 ,
b11000010 .
b101010001000 /
b11 1
b11000010 2
b101010001000 3

#6250
0!
0(

#6300
1!
b1000010011000 %
1(
b100 ,
b11010011 .
b1000010011000 /
b100 1
b11010011 2
b1000010011000 3

#6350
0!
0(

#6400
1!
b1011100110000 %
1(
b101 ,
b11100100 .
b1011100110000 /
b101 1
b11100100 2
b1011100110000 3

#6450
0!
0(

#6500
1!
b1111001010000 %
1(
b110 ,
b11110101 .
b1111001010000 /
b110 1
b11110101 2
b1111001010000 3

#6550
0!
0(

#6600
1!
b10010111111000 %
1(
b111 ,
b110 .
b10010111111000 /
b111 1
b110 2
b10010111111000 3

#6650
0!
0(

#6700
1!
b10011000101000 %
1(
b0 ,
b10111 .
b10011000101000 /
b0 1
b10111 2
b10011000101000 3

#6750
0!
0(

#6800
1!
0#
b10 &
1(
0*
b10011011100000 5
b10011000101000 6

#6850
0!
0(

#6900
1!
1"
b0 %
1(
1)
b0 .
b0 /
b0 2
b0 3

#6950
0!
0(

#7000
1!
1(

#7050
0!
0(

#7100
1!
1(

#7150
0!
0(

#7200
1!
1(

#7250
0!
0(

#7300
1!
1(

#7350
0!
0(

#7400
1!
1(

#7450
0!
0(

#7500
1!
1(

#7550
0!
0(

#7600
1!
1(

#7650
0!
0(

#7700
1!
1(

#7750
0!
0(

#7800
1!
1(

#7850
0!
0(

#7900
1!
1(

#7950
0!
0(

#8000
1!
1(

#8050
0!
0(

#8100
1!
1(

#8150
0!
0(

#8200
1!
1(

#8250
0!
0(

#8300
1!
1(

#8350
0!
0(

#8400
1!
1(

#8450
0!
0(

#8500
1!
1(

#8550
0!
0(

#8600
1!
1(

#8650
0!
0(

#8700
1!
1(

#8750
0!
0(

#8800
1!
1(

#8850
0!
0(

#8900
1!
0"
1#
b1011 $
b11010101110100 '
1(
0)
1*
b1011 +
b1 ,
b10100000 .
b1 1
b10100000 2
b1000 4

#8950
0!
0(

#9000
1!
b11011100000 %
1(
b10 ,
b10110001 .
b11011100000 /
b10 1
b10110001 2
b11011100000 3

#9050
0!
0(

#9100
1!
b111001111011 %
1(
b11 ,
b11000010 .
b111001111011 /
b11 1
b11000010 2
b111001111011 3

#9150
0!
0(

#9200
1!
b1011011010001 %
1(
b100 ,
b11010011 .
b1011011010001 /
b100 1
b11010011 2
b1011011010001 3

#9250
0!
0(

#9300
1!
b1111111100010 %
1(
b101 ,
b11100100 .
b1111111100010 /
b101 1
b11100100 2
b1111111100010 3

#9350
0!
0(

#9400
1!
b10100110101110 %
1(
b110 ,
b11110101 .
b10100110101110 /
b110 1
b11110101 2
b10100110101110 3

#9450
0!
0(

#9500
1!
b11010000110101 %
1(
b111 ,
b110 .
b11010000110101 /
b111 1
b110 2
b11010000110101 3

#9550
0!
0(

#9600
1!
b11010001110111 %
1(
b0 ,
b10111 .
b11010001110111 /
b0 1
b10111 2
b11010001110111 3

#9650
0!
0(

#9700
1!
0#
b11 &
1(
0*
b11010101110100 5
b11010001110111 6

#9750
0!
0(

#9800
1!
1"
b0 %
1(
1)
b0 .
b0 /
b0 2
b0 3

#9850
0!
0(

#9900
1!
1(

#9950
0!
0(

#10000
1!
1(

#10050
0!
0(

#10100
1!
1(

#10150
0!
0(

#10200
1!
1(

#10250
0!
0(

#10300
1!
1(

#10350
0!
0(

#10400
1!
1(

#10450
0!
0(

#10500
1!
1(

#10550
0!
0(

#10600
1!
1(

#10650
0!
0(

#10700
1!
1(

#10750
0!
0(

#10800
1!
1(

#10850
0!
0(

#10900
1!
1(

#10950
0!
0(

#11000
1!
1(

#11050
0!
0(

#11100
1!
1(

#11150
0!
0(

#11200
1!
1(

#11250
0!
0(

#11300
1!
1(

#11350
0!
0(

#11400
1!
1(

#11450
0!
0(

#11500
1!
1(

#11550
0!
0(

#11600
1!
1(

#11650
0!
0(

#11700
1!
1(

#11750
0!
0(

#11800
1!
0"
1#
b1111 $
b100100011100100 '
1(
0)
1*
b1111 +
b1 ,
b10100000 .
b1 1
b10100000 2
b1000 4

#11850
0!
0(

#11900
1!
b100101100000 %
1(
b10 ,
b10110001 .
b100101100000 /
b10 1
b10110001 2
b100101100000 3

#11950
0!
0(

#12000
1!
b1001110111111 %
1(
b11 ,
b11000010 .
b1001110111111 /
b11 1
b11000010 2
b1001110111111 3

#12050
0!
0(

#12100
1!
b1111100011101 %
1(
b100 ,
b11010011 .
b1111100011101 /
b100 1
b11010011 2
b1111100011101 3

#12150
0!
0(

#12200
1!
b10101101111010 %
1(
b101 ,
b11100100 .
b10101101111010 /
b101 1
b11100100 2
b10101101111010 3

#12250
0!
0(

#12300
1!
b11100011010110 %
1(
b110 ,
b11110101 .
b11100011010110 /
b110 1
b11110101 2
b11100011010110 3

#12350
0!
0(

#12400
1!
b100011100110001 %
1(
b111 ,
b110 .
b100011100110001 /
b111 1
b110 2
b100011100110001 3

#12450
0!
0(

#12500
1!
b100011110001011 %
1(
b0 ,
b10111 .
b100011110001011 /
b0 1
b10111 2
b100011110001011 3

#12550
0!
0(

#12600
1!
0#
b100 &
1(
0*
b100100011100100 5
b100011110001011 6

#12650
0!
0(

#12700
1!
1"
b0 %
1(
1)
b0 .
b0 /
b0 2
b0 3

#12750
0!
0(

#12800
1!
1(

#12850
0!
0(

#12900
1!
1(

#12950
0!
0(

#13000
1!
1(

#13050
0!
0(

#13100
1!
1(

#13150
0!
0(

#13200
1!
1(

#13250
0!
0(

#13300
1!
1(

#13350
0!
0(

#13400
1!
1(

#13450
0!
0(

#13500
1!
1(

#13550
0!
0(

#13600
1!
1(

#13650
0!
0(

#13700
1!
1(

#13750
0!
0(

#13800
1!
1(

#13850
0!
0(

#13900
1!
1(

#13950
0!
0(

#14000
1!
1(

#14050
0!
0(

#14100
1!
1(

#14150
0!
0(

#14200
1!
1(

#14250
0!
0(

#14300
1!
1(

#14350
0!
0(

#14400
1!
1(

#14450
0!
0(

#14500
1!
1(

#14550
0!
0(

#14600
1!
1(

#14650
0!
0(

#14700
1!
0"
1#
b1 $
b10011011100 '
1(
0)
1*
b1 +
b1 ,
b10100000 .
b1 1
b10100000 2
b1000 4

#14750
0!
0(

#14800
1!
b10100000 %
1(
b10 ,
b10110001 .
b10100000 /
b10 1
b10110001 2
b10100000 3

#14850
0!
0(

#14900
1!
b101010001 %
1(
b11 ,
b11000010 .
b101010001 /
b11 1
b11000010 2
b101010001 3

#14950
0!
0(

#15000
1!
b1000010011 %
1(
b100 ,
b11010011 .
b1000010011 /
b100 1
b11010011 2
b1000010011 3

#15050
0!
0(

#15100
1!
b1011100110 %
1(
b101 ,
b11100100 .
b1011100110 /
b101 1
b11100100 2
b1011100110 3

#15150
0!
0(

#15200
1!
b1111001010 %
1(
b110 ,
b11110101 .
b1111001010 /
b110 1
b11110101 2
b1111001010 3

#15250
0!
0(

#15300
1!
b10010111111 %
1(
b111 ,
b110 .
b10010111111 /
b111 1
b110 2
b10010111111 3

#15350
0!
0(

#15400
1!
b10011000101 %
1(
b0 ,
b10111 .
b10011000101 /
b0 1
b10111 2
b10011000101 3

#15450
0!
0(

#15500
1!
0#
b101 &
1(
0*
b10011011100 5
b10011000101 6

#15550
0!
0(

#15600
1!
1"
b0 %
1(
1)
b0 .
b0 /
b0 2
b0 3

#15650
0!
0(

#15700
1!
1(

#15750
0!
0(

#15800
1!
1(

#15850
0!
0(

#15900
1!
1(

#15950
0!
0(

#16000
1!
1(

#16050
0!
0(

#16100
1!
1(

#16150
0!
0(

#16200
1!
1(

#16250
0!
0(

#16300
1!
1(

#16350
0!
0(

#16400
1!
1(

#16450
0!
0(

#16500
1!
1(

#16550
0!
0(

#16600
1!
1(

#16650
0!
0(

#16700
1!
1(

#16750
0!
0(

#16800
1!
1(

#16850
0!
0(

#16900
1!
1(

#16950
0!
0(

#17000
1!
1(

#17050
0!
0(

#17100
1!
1(

#17150
0!
0(

#17200
1!
1(

#17250
0!
0(

#17300
1!
1(

#17350
0!
0(

#17400
1!
1(

#17450
0!
0(

#17500
1!
1(

#17550
0!
0(

#17600
1!
0"
1#
b1110 $
b100010000001000 '
1(
0)
1*
b1110 +
b1 ,
b10100000 .
b1 1
b10100000 2
b1000 4

#17650
0!
0(

#17700
1!
b100011000000 %
1(
b10 ,
b10110001 .
b100011000000 /
b10 1
b10110001 2
b100011000000 3

#17750
0!
0(

#17800
1!
b1001001101110 %
1(
b11 ,
b11000010 .
b1001001101110 /
b11 1
b11000010 2
b1001001101110 3

#17850
0!
0(

#17900
1!
b1110100001010 %
1(
b100 ,
b11010011 .
b1110100001010 /
b100 1
b11010011 2
b1110100001010 3

#17950
0!
0(

#18000
1!
b10100010010100 %
1(
b101 ,
b11100100 .
b10100010010100 /
b101 1
b11100100 2
b10100010010100 3

#18050
0!
0(

#18100
1!
b11010100001100 %
1(
b110 ,
b11110101 .
b11010100001100 /
b110 1
b11110101 2
b11010100001100 3

#18150
0!
0(

#18200
1!
b100001001110010 %
1(
b111 ,
b110 .
b100001001110010 /
b111 1
b110 2
b100001001110010 3

#18250
0!
0(

#18300
1!
b100001011000110 %
1(
b0 ,
b10111 .
b100001011000110 /
b0 1
b10111 2
b100001011000110 3

#18350
0!
0(

#18400
1!
0#
b110 &
1(
0*
b100010000001000 5
b100001011000110 6

#18450
0!
0(

#18500
1!
1"
b0 %
1(
1)
b0 .
b0 /
b0 2
b0 3

#18550
0!
0(

#18600
1!
1(

#18650
0!
0(

#18700
1!
1(

#18750
0!
0(

#18800
1!
1(

#18850
0!
0(

#18900
1!
1(

#18950
0!
0(

#19000
1!
1(

#19050
0!
0(

#19100
1!
1(

#19150
0!
0(

#19200
1!
1(

#19250
0!
0(

#19300
1!
1(

#19350
0!
0(

#19400
1!
1(

#19450
0!
0(

#19500
1!
1(

#19550
0!
0(

#19600
1!
1(

#19650
0!
0(

#19700
1!
1(

#19750
0!
0(

#19800
1!
1(

#19850
0!
0(

#19900
1!
1(

#19950
0!
0(

#20000
1!
1(

#20050
0!
0(

#20100
1!
1(

#20150
0!
0(

#20200
1!
1(

#20250
0!
0(

#20300
1!
1(

#20350
0!
0(

#20400
1!
1(

#20450
0!
0(

#20500
1!
0"
1#
b1111 $
b100100011100100 '
1(
0)
1*
b1111 +
b1 ,
b10100000 .
b1 1
b10100000 2
b1000 4

#20550
0!
0(

#20600
1!
b100101100000 %
1(
b10 ,
b10110001 .
b100101100000 /
b10 1
b10110001 2
b100101100000 3

#20650
0!
0(

#20700
1!
b1001110111111 %
1(
b11 ,
b11000010 .
b1001110111111 /
b11 1
b11000010 2
b1001110111111 3

#20750
0!
0(

#20800
1!
b1111100011101 %
1(
b100 ,
b11010011 .
b1111100011101 /
b100 1
b11010011 2
b1111100011101 3

#20850
0!
0(

#20900
1!
b10101101111010 %
1(
b101 ,
b11100100 .
b10101101111010 /
b101 1
b11100100 2
b10101101111010 3

#20950
0!
0(

#21000
1!
b11100011010110 %
1(
b110 ,
b11110101 .
b11100011010110 /
b110 1
b11110101 2
b11100011010110 3

#21050
0!
0(

#21100
1!
b100011100110001 %
1(
b111 ,
b110 .
b100011100110001 /
b111 1
b110 2
b100011100110001 3

#21150
0!
0(

#21200
1!
b100011110001011 %
1(
b0 ,
b10111 .
b100011110001011 /
b0 1
b10111 2
b100011110001011 3

#21250
0!
0(

#21300
1!
0#
b111 &
1(
0*
b100100011100100 5
b100011110001011 6

#21350
0!
0(

#21400
1!
1"
b0 %
1(
1)
b0 .
b0 /
b0 2
b0 3

#21450
0!
0(

#21500
1!
1(

#21550
0!
0(

#21600
1!
1(

#21650
0!
0(

#21700
1!
1(

#21750
0!
0(

#21800
1!
1(

#21850
0!
0(

#21900
1!
1(

#21950
0!
0(

#22000
1!
1(

#22050
0!
0(

#22100
1!
1(

#22150
0!
0(

#22200
1!
1(

#22250
0!
0(

#22300
1!
1(

#22350
0!
0(

#22400
1!
1(

#22450
0!
0(

#22500
1!
1(

#22550
0!
0(

#22600
1!
1(

#22650
0!
0(

#22700
1!
1(

#22750
0!
0(

#22800
1!
1(

#22850
0!
0(

#22900
1!
1(

#22950
0!
0(

#23000
1!
1(

#23050
0!
0(

#23100
1!
1(

#23150
0!
0(

#23200
1!
1(

#23250
0!
0(

#23300
1!
1(

#23350
0!
0(

#23400
1!
0"
1#
b1011 $
b11010101110100 '
1(
0)
1*
b1011 +
b1 ,
b10100000 .
b1 1
b10100000 2
b1000 4

#23450
0!
0(

#23500
1!
b11011100000 %
1(
b10 ,
b10110001 .
b11011100000 /
b10 1
b10110001 2
b11011100000 3

#23550
0!
0(

#23600
1!
b111001111011 %
1(
b11 ,
b11000010 .
b111001111011 /
b11 1
b11000010 2
b111001111011 3

#23650
0!
0(

#23700
1!
b1011011010001 %
1(
b100 ,
b11010011 .
b1011011010001 /
b100 1
b11010011 2
b1011011010001 3

#23750
0!
0(

#23800
1!
b1111111100010 %
1(
b101 ,
b11100100 .
b1111111100010 /
b101 1
b11100100 2
b1111111100010 3

#23850
0!
0(

#23900
1!
b10100110101110 %
1(
b110 ,
b11110101 .
b10100110101110 /
b110 1
b11110101 2
b10100110101110 3

#23950
0!
0(

#24000
1!
b11010000110101 %
1(
b111 ,
b110 .
b11010000110101 /
b111 1
b110 2
b11010000110101 3

#24050
0!
0(

#24100
1!
b11010001110111 %
1(
b0 ,
b10111 .
b11010001110111 /
b0 1
b10111 2
b11010001110111 3

#24150
0!
0(

#24200
1!
0#
b1000 &
1(
0*
b11010101110100 5
b11010001110111 6

#24250
0!
0(

#24300
1!
1"
b0 %
1(
1)
b0 .
b0 /
b0 2
b0 3

#24350
0!
0(

#24400
1!
1(

#24450
0!
0(

#24500
1!
1(

#24550
0!
0(

#24600
1!
1(

#24650
0!
0(

#24700
1!
1(

#24750
0!
0(

#24800
1!
1(

#24850
0!
0(

#24900
1!
1(

#24950
0!
0(

#25000
1!
1(

#25050
0!
0(

#25100
1!
1(

#25150
0!
0(

#25200
1!
1(

#25250
0!
0(

#25300
1!
1(

#25350
0!
0(

#25400
1!
1(

#25450
0!
0(

#25500
1!
1(

#25550
0!
0(

#25600
1!
1(

#25650
0!
0(

#25700
1!
1(

#25750
0!
0(

#25800
1!
1(

#25850
0!
0(

#25900
1!
1(

#25950
0!
0(

#26000
1!
1(

#26050
0!
0(

#26100
1!
1(

#26150
0!
0(

#26200
1!
1(

#26250
0!
0(

#26300
1!
0"
1#
b110 $
b1110100101000 '
1(
0)
1*
b110 +
b1 ,
b10100000 .
b1 1
b10100000 2
b1000 4

#26350
0!
0(

#26400
1!
b1111000000 %
1(
b10 ,
b10110001 .
b1111000000 /
b10 1
b10110001 2
b1111000000 3

#26450
0!
0(

#26500
1!
b11111100110 %
1(
b11 ,
b11000010 .
b11111100110 /
b11 1
b11000010 2
b11111100110 3

#26550
0!
0(

#26600
1!
b110001110010 %
1(
b100 ,
b11010011 .
b110001110010 /
b100 1
b11010011 2
b110001110010 3

#26650
0!
0(

#26700
1!
b1000101100100 %
1(
b101 ,
b11100100 .
b1000101100100 /
b101 1
b11100100 2
b1000101100100 3

#26750
0!
0(

#26800
1!
b1011010111100 %
1(
b110 ,
b11110101 .
b1011010111100 /
b110 1
b11110101 2
b1011010111100 3

#26850
0!
0(

#26900
1!
b1110001111010 %
1(
b111 ,
b110 .
b1110001111010 /
b111 1
b110 2
b1110001111010 3

#26950
0!
0(

#27000
1!
b1110010011110 %
1(
b0 ,
b10111 .
b1110010011110 /
b0 1
b10111 2
b1110010011110 3

#27050
0!
0(

#27100
1!
0#
b1001 &
1(
0*
b1110100101000 5
b1110010011110 6

#27150
0!
0(

#27200
1!
1"
b0 %
1(
1)
b0 .
b0 /
b0 2
b0 3

#27250
0!
0(

#27300
1!
1(

#27350
0!
0(

#27400
1!
1(

#27450
0!
0(

#27500
1!
1(

#27550
0!
0(

#27600
1!
1(

#27650
0!
0(

#27700
1!
1(

#27750
0!
0(

#27800
1!
1(

#27850
0!
0(

#27900
1!
1(

#27950
0!
0(

#28000
1!
1(

#28050
0!
0(

#28100
1!
1(

#28150
0!
0(

#28200
1!
1(

#28250
0!
0(

#28300
1!
1(

#28350
0!
0(

#28400
1!
1(

#28450
0!
0(

#28500
1!
1(

#28550
0!
0(

#28600
1!
1(

#28650
0!
0(

#28700
1!
1(

#28750
0!
0(

#28800
1!
1(

#28850
0!
0(

#28900
1!
1(

#28950
0!
0(

#29000
1!
1(

#29050
0!
0(

#29100
1!
1(

#29150
0!
0(

#29200
1!
0"
1#
b1011 $
b11010101110100 '
1(
0)
1*
b1011 +
b1 ,
b10100000 .
b1 1
b10100000 2
b1000 4

#29250
0!
0(

#29300
1!
b11011100000 %
1(
b10 ,
b10110001 .
b11011100000 /
b10 1
b10110001 2
b11011100000 3

#29350
0!
0(

#29400
1!
b111001111011 %
1(
b11 ,
b11000010 .
b111001111011 /
b11 1
b11000010 2
b111001111011 3

#29450
0!
0(

#29500
1!
b1011011010001 %
1(
b100 ,
b11010011 .
b1011011010001 /
b100 1
b11010011 2
b1011011010001 3

#29550
0!
0(

#29600
1!
b1111111100010 %
1(
b101 ,
b11100100 .
b1111111100010 /
b101 1
b11100100 2
b1111111100010 3

#29650
0!
0(

#29700
1!
b10100110101110 %
1(
b110 ,
b11110101 .
b10100110101110 /
b110 1
b11110101 2
b10100110101110 3

#29750
0!
0(

#29800
1!
b11010000110101 %
1(
b111 ,
b110 .
b11010000110101 /
b111 1
b110 2
b11010000110101 3

#29850
0!
0(

#29900
1!
b11010001110111 %
1(
b0 ,
b10111 .
b11010001110111 /
b0 1
b10111 2
b11010001110111 3

#29950
0!
0(

#30000
1!
0#
b1010 &
1(
0*
b11010101110100 5
b11010001110111 6

#30050
0!
0(

#30100
1!
1"
b0 %
1(
1)
b0 .
b0 /
b0 2
b0 3

#30150
0!
0(

#30200
1!
1(

#30250
0!
0(

#30300
1!
1(

#30350
0!
0(

#30400
1!
1(

#30450
0!
0(

