hw4/src/mac.v
module mac
#(
    parameter DATA_WIDTH = 16
)(
    input wire i_clk,
    input wire i_rst,
    input wire i_en,
    input wire [DATA_WIDTH-1:0] iv_a,
    input wire [DATA_WIDTH-1:0] iv_b,
    output wire [DATA_WIDTH-1:0] ov_c
);

    reg [DATA_WIDTH*2-1:0] sum_full;
    assign ov_c = sum_full[DATA_WIDTH-1:0];

    always @(posedge i_clk) begin
        if (i_rst) begin
            sum_full <= 0;
        end else if (i_en) begin
            sum_full <= sum_full + iv_a * iv_b;
        end
    end

endmodule

hw4/src/single_port_ram.v
module single_port_ram
#(
    parameter DATA_WIDTH = 24,
    parameter ADDR_WIDTH = 8
)(
    input wire i_clk,
    input wire i_rst,
    input wire i_en,
    input wire i_we,
    input wire [ADDR_WIDTH-1:0] iv_addr,
    input wire [DATA_WIDTH-1:0] iv_din,
    output reg [DATA_WIDTH-1:0] ov_dout
);
    reg [DATA_WIDTH-1:0] RAM [0:2**ADDR_WIDTH-1];

    initial begin
        RAM[0] = 16'd111;
        RAM[1] = 16'd222;
        RAM[2] = 16'd333;
        RAM[3] = 16'd25;
        RAM[4] = 16'd26;
        RAM[5] = 16'd27;
        RAM[6] = 16'd28;
        RAM[7] = 16'd29;
    end

    always @(posedge i_clk) begin
        if (i_rst) begin // reset output register
            ov_dout <= 0;
        end else if(i_en) begin
            if (i_we) begin // write
                RAM[iv_addr] <= iv_din;
                ov_dout <= iv_din;
            end else begin // read
                ov_dout <= RAM[iv_addr];
            end
        end
    end

endmodule

hw4/src/memory_modelling.v
module memory_modelling
#(
    parameter DATA_WIDTH = 16,
    parameter RAM_DEPTH = 8
)(
    input wire i_clk,
    input wire i_rst,
    input wire i_en,
    input wire [DATA_WIDTH-1:0] iv_b,
    output wire [DATA_WIDTH-1:0] ov_sum
);

    localparam ADDR_WIDTH = $clog2(RAM_DEPTH);
    reg [ADDR_WIDTH-1:0] ram_addr;
    wire [DATA_WIDTH-1:0] ram_din;
    wire [DATA_WIDTH-1:0] ram_dout;

    single_port_ram
    #(
        .DATA_WIDTH(DATA_WIDTH),
        .ADDR_WIDTH(ADDR_WIDTH)
    ) spram_inst (
        .i_clk(i_clk),
        .i_rst(i_rst),
        .i_en(i_en),
        .i_we(0),
        .iv_addr(ram_addr),
        .iv_din(ram_din),
        .ov_dout(ram_dout)
    );

    wire [DATA_WIDTH-1:0] sum;
    assign ov_sum = sum;

    mac
    #(
        .DATA_WIDTH(DATA_WIDTH)
    ) mac_inst (
        .i_clk(i_clk),
        .i_rst(i_rst),
        .i_en(i_en),
        .iv_a(ram_dout),
        .iv_b(iv_b),
        .ov_c(sum)
    );

    always @(posedge i_clk) begin
        if (i_rst) begin
            ram_addr <= 0;
        end else if (i_en) begin
            ram_addr <= ram_addr + 1;
        end
    end

endmodule

hw4/src/top_level.v
module top_level
#(
    parameter DATA_WIDTH = 16,
    parameter RAM_DEPTH = 8
)(
    input wire i_clk,
    input wire i_rst,
    input wire i_en,
    input wire [DATA_WIDTH-1:0] iv_b,
    output wire [DATA_WIDTH-1:0] ov_sum
);

    memory_modelling
    #(
        .DATA_WIDTH(DATA_WIDTH),
        .RAM_DEPTH(RAM_DEPTH)
    ) memory_modelling_inst (
        .i_clk(i_clk),
        .i_rst(i_rst),
        .i_en(i_en),
        .iv_b(iv_b),
        .ov_sum(ov_sum)
    );

endmodule

hw4/verif/tb_memory_modelling.sv

module tb_memory_modelling;

    localparam DATA_WIDTH = 16;
    localparam RAM_DEPTH = 8;
    reg tb_clk;
    reg tb_rst;
    reg tb_en;
    reg [DATA_WIDTH-1:0] tb_a [0:RAM_DEPTH-1];
    reg [DATA_WIDTH-1:0] tb_b;

    wire [DATA_WIDTH-1:0] dut_sum;

    int num_errors = 0;
    reg [DATA_WIDTH:0] tb_exp_sum;

    top_level
    #(
        .DATA_WIDTH(DATA_WIDTH),
        .RAM_DEPTH(RAM_DEPTH)
    ) top_level_inst (

        .i_clk(tb_clk),
        .i_rst(tb_rst),
        .i_en(tb_en),
        .iv_b(tb_b),
        .ov_sum(dut_sum)
    );

    task assert_and_report(input [DATA_WIDTH-1:0] expected, input [DATA_WIDTH-1:0] actual);
    begin
        if (actual == expected) begin
            $display(" SUCCESS!\n  Expected: %b\n  Actual:   %b", expected, actual);
        end else begin
            $display(" FAILURE!\n  Expected: %b\n  Actual:   %b", expected, actual);
            num_errors = num_errors + 1;
        end
    end
    endtask // assert_and_report

    always_comb begin
        tb_exp_sum = '0;
        for (int i = 0; i < RAM_DEPTH; i = i + 1) begin
            tb_exp_sum += tb_b * tb_a[i];
        end
    end

    always #5 tb_clk = ~tb_clk;
    initial begin
        $dumpfile("waveform.vcd");
        $dumpvars;

        tb_a[0] = 16'd111;
        tb_a[1] = 16'd222;
        tb_a[2] = 16'd333;
        tb_a[3] = 16'd25;
        tb_a[4] = 16'd26;
        tb_a[5] = 16'd27;
        tb_a[6] = 16'd28;
        tb_a[7] = 16'd29;

        num_errors = 0;
        tb_clk = 1;
        tb_rst = 1;
        tb_en = 0;

        @(posedge tb_clk);
        tb_rst = 0;
        tb_en = 0;
        @(posedge tb_clk);

        repeat (100) begin
            tb_b = $urandom() & 6'b111111;
            repeat(9) begin
                tb_rst = 0;
                tb_en = 1;
                @(posedge tb_clk);
            end
            tb_en = 0;
            assert_and_report(tb_exp_sum, dut_sum);
            @(posedge tb_clk);
            tb_rst = 1;
            $display();
            repeat (20) begin
                @(posedge tb_clk);
            end
        end

        $display();
        $display("Total number of errors: %d", num_errors);
        $display();

        $finish;
    end // initial


    initial begin
        #1ms;
        $display("Simulation terminated after 1 millisecond.");
        $finish;
    end // initial
endmodule

hw4/sim/waveform.vcd
$date
   Sun Dec 15 16:56:33 2024
$end

$version
  2023.2.2
  $dumpfile ("waveform.vcd") 
$end

$timescale
  1ns
$end

$scope module tb_memory_modelling $end
$var reg 1 ! tb_clk $end
$var reg 1 " tb_rst $end
$var reg 1 # tb_en $end
$var reg 16 $ tb_b [15:0] $end
$var wire 16 % dut_sum [15:0] $end
$var reg 32 & num_errors [31:0] $end
$var reg 17 ' tb_exp_sum [16:0] $end
$scope module top_level_inst $end
$var wire 1 ( i_clk $end
$var wire 1 ) i_rst $end
$var wire 1 * i_en $end
$var wire 16 + iv_b [15:0] $end
$var wire 16 % ov_sum [15:0] $end
$scope module memory_modelling_inst $end
$var wire 1 ( i_clk $end
$var wire 1 ) i_rst $end
$var wire 1 * i_en $end
$var wire 16 + iv_b [15:0] $end
$var wire 16 % ov_sum [15:0] $end
$var reg 3 , ram_addr [2:0] $end
$var wire 16 - ram_din [15:0] $end
$var wire 16 . ram_dout [15:0] $end
$var wire 16 / sum [15:0] $end
$scope module spram_inst $end
$var wire 1 ( i_clk $end
$var wire 1 ) i_rst $end
$var wire 1 * i_en $end
$var wire 1 0 i_we $end
$var wire 3 1 iv_addr [2:0] $end
$var wire 16 - iv_din [15:0] $end
$var reg 16 2 ov_dout [15:0] $end
$upscope $end
$scope module mac_inst $end
$var wire 1 ( i_clk $end
$var wire 1 ) i_rst $end
$var wire 1 * i_en $end
$var wire 16 . iv_a [15:0] $end
$var wire 16 + iv_b [15:0] $end
$var wire 16 / ov_c [15:0] $end
$var reg 32 3 sum_full [31:0] $end
$upscope $end
$upscope $end
$upscope $end
$scope begin Block43_5 $end
$var reg 32 4 i [31:0] $end
$upscope $end
$scope task assert_and_report $end
$var reg 16 5 expected [15:0] $end
$var reg 16 6 actual [15:0] $end
$upscope $end
$upscope $end
$enddefinitions $end

#0
$dumpvars
1!
1"
0#
bx $
b0 %
b0 &
bx '
1(
1)
0*
bx +
b0 ,
bz -
b0 .
b0 /
00
b0 1
b0 2
b0 3
b1000 4
bx 5
bx 6
$end

#50
0!
0(

#100
1!
0"
1(
0)

#150
0!
0(

#200
1!
1#
b10000 $
b11001000010000 '
1(
1*
b10000 +
b1 ,
b1101111 .
b1 1
b1101111 2
b1000 4

#250
0!
0(

#300
1!
b11011110000 %
1(
b10 ,
b11011110 .
b11011110000 /
b10 1
b11011110 2
b11011110000 3

#350
0!
0(

#400
1!
b1010011010000 %
1(
b11 ,
b101001101 .
b1010011010000 /
b11 1
b101001101 2
b1010011010000 3

#450
0!
0(

#500
1!
b10100110100000 %
1(
b100 ,
b11001 .
b10100110100000 /
b100 1
b11001 2
b10100110100000 3

#550
0!
0(

#600
1!
b10101100110000 %
1(
b101 ,
b11010 .
b10101100110000 /
b101 1
b11010 2
b10101100110000 3

#650
0!
0(

#700
1!
b10110011010000 %
1(
b110 ,
b11011 .
b10110011010000 /
b110 1
b11011 2
b10110011010000 3

#750
0!
0(

#800
1!
b10111010000000 %
1(
b111 ,
b11100 .
b10111010000000 /
b111 1
b11100 2
b10111010000000 3

#850
0!
0(

#900
1!
b11000001000000 %
1(
b0 ,
b11101 .
b11000001000000 /
b0 1
b11101 2
b11000001000000 3

#950
0!
0(

#1000
1!
b11001000010000 %
1(
b1 ,
b1101111 .
b11001000010000 /
b1 1
b1101111 2
b11001000010000 3

#1050
0!
0(

#1100
1!
0#
1(
0*
b11001000010000 5
b11001000010000 6

#1150
0!
0(

#1200
1!
1"
b0 %
1(
1)
b0 ,
b0 .
b0 /
b0 1
b0 2
b0 3

#1250
0!
0(

#1300
1!
1(

#1350
0!
0(

#1400
1!
1(

#1450
0!
0(

#1500
1!
1(

#1550
0!
0(

#1600
1!
1(

#1650
0!
0(

#1700
1!
1(

#1750
0!
0(

#1800
1!
1(

#1850
0!
0(

#1900
1!
1(

#1950
0!
0(

#2000
1!
1(

#2050
0!
0(

#2100
1!
1(

#2150
0!
0(

#2200
1!
1(

#2250
0!
0(

#2300
1!
1(

#2350
0!
0(

#2400
1!
1(

#2450
0!
0(

#2500
1!
1(

#2550
0!
0(

#2600
1!
1(

#2650
0!
0(

#2700
1!
1(

#2750
0!
0(

#2800
1!
1(

#2850
0!
0(

#2900
1!
1(

#2950
0!
0(

#3000
1!
1(

#3050
0!
0(

#3100
1!
1(

#3150
0!
0(

#3200
1!
0"
1#
b101010 $
b1000001101101010 '
1(
0)
1*
b101010 +
b1 ,
b1101111 .
b1 1
b1101111 2
b1000 4

#3250
0!
0(

#3300
1!
b1001000110110 %
1(
b10 ,
b11011110 .
b1001000110110 /
b10 1
b11011110 2
b1001000110110 3

#3350
0!
0(

#3400
1!
b11011010100010 %
1(
b11 ,
b101001101 .
b11011010100010 /
b11 1
b101001101 2
b11011010100010 3

#3450
0!
0(

#3500
1!
b110110101000100 %
1(
b100 ,
b11001 .
b110110101000100 /
b100 1
b11001 2
b110110101000100 3

#3550
0!
0(

#3600
1!
b111000101011110 %
1(
b101 ,
b11010 .
b111000101011110 /
b101 1
b11010 2
b111000101011110 3

#3650
0!
0(

#3700
1!
b111010110100010 %
1(
b110 ,
b11011 .
b111010110100010 /
b110 1
b11011 2
b111010110100010 3

#3750
0!
0(

#3800
1!
b111101000010000 %
1(
b111 ,
b11100 .
b111101000010000 /
b111 1
b11100 2
b111101000010000 3

#3850
0!
0(

#3900
1!
b111111010101000 %
1(
b0 ,
b11101 .
b111111010101000 /
b0 1
b11101 2
b111111010101000 3

#3950
0!
0(

#4000
1!
b1000001101101010 %
1(
b1 ,
b1101111 .
b1000001101101010 /
b1 1
b1101111 2
b1000001101101010 3

#4050
0!
0(

#4100
1!
0#
1(
0*
b1000001101101010 5
b1000001101101010 6

#4150
0!
0(

#4200
1!
1"
b0 %
1(
1)
b0 ,
b0 .
b0 /
b0 1
b0 2
b0 3

#4250
0!
0(

#4300
1!
1(

#4350
0!
0(

#4400
1!
1(

#4450
0!
0(

#4500
1!
1(

#4550
0!
0(

#4600
1!
1(

#4650
0!
0(

#4700
1!
1(

#4750
0!
0(

#4800
1!
1(

#4850
0!
0(

#4900
1!
1(

#4950
0!
0(

#5000
1!
1(

#5050
0!
0(

#5100
1!
1(

#5150
0!
0(

#5200
1!
1(

#5250
0!
0(

#5300
1!
1(

#5350
0!
0(

#5400
1!
1(

#5450
0!
0(

#5500
1!
1(

#5550
0!
0(

#5600
1!
1(

#5650
0!
0(

#5700
1!
1(

#5750
0!
0(

#5800
1!
1(

#5850
0!
0(

#5900
1!
1(

#5950
0!
0(

#6000
1!
1(

#6050
0!
0(

#6100
1!
1(

#6150
0!
0(

#6200
1!
0"
1#
b101000 $
b111110100101000 '
1(
0)
1*
b101000 +
b1 ,
b1101111 .
b1 1
b1101111 2
b1000 4

#6250
0!
0(

#6300
1!
b1000101011000 %
1(
b10 ,
b11011110 .
b1000101011000 /
b10 1
b11011110 2
b1000101011000 3

#6350
0!
0(

#6400
1!
b11010000001000 %
1(
b11 ,
b101001101 .
b11010000001000 /
b11 1
b101001101 2
b11010000001000 3

#6450
0!
0(

#6500
1!
b110100000010000 %
1(
b100 ,
b11001 .
b110100000010000 /
b100 1
b11001 2
b110100000010000 3

#6550
0!
0(

#6600
1!
b110101111111000 %
1(
b101 ,
b11010 .
b110101111111000 /
b101 1
b11010 2
b110101111111000 3

#6650
0!
0(

#6700
1!
b111000000001000 %
1(
b110 ,
b11011 .
b111000000001000 /
b110 1
b11011 2
b111000000001000 3

#6750
0!
0(

#6800
1!
b111010001000000 %
1(
b111 ,
b11100 .
b111010001000000 /
b111 1
b11100 2
b111010001000000 3

#6850
0!
0(

#6900
1!
b111100010100000 %
1(
b0 ,
b11101 .
b111100010100000 /
b0 1
b11101 2
b111100010100000 3

#6950
0!
0(

#7000
1!
b111110100101000 %
1(
b1 ,
b1101111 .
b111110100101000 /
b1 1
b1101111 2
b111110100101000 3

#7050
0!
0(

#7100
1!
0#
1(
0*
b111110100101000 5
b111110100101000 6

#7150
0!
0(

#7200
1!
1"
b0 %
1(
1)
b0 ,
b0 .
b0 /
b0 1
b0 2
b0 3

#7250
0!
0(

#7300
1!
1(

#7350
0!
0(

#7400
1!
1(

#7450
0!
0(

#7500
1!
1(

#7550
0!
0(

#7600
1!
1(

#7650
0!
0(

#7700
1!
1(

#7750
0!
0(

#7800
1!
1(

#7850
0!
0(

#7900
1!
1(

#7950
0!
0(

#8000
1!
1(

#8050
0!
0(

#8100
1!
1(

#8150
0!
0(

#8200
1!
1(

#8250
0!
0(

#8300
1!
1(

#8350
0!
0(

#8400
1!
1(

#8450
0!
0(

#8500
1!
1(

#8550
0!
0(

#8600
1!
1(

#8650
0!
0(

#8700
1!
1(

#8750
0!
0(

#8800
1!
1(

#8850
0!
0(

#8900
1!
1(

#8950
0!
0(

#9000
1!
1(

#9050
0!
0(

#9100
1!
1(

#9150
0!
0(

#9200
1!
0"
1#
b101011 $
b1000011010001011 '
1(
0)
1*
b101011 +
b1 ,
b1101111 .
b1 1
b1101111 2
b1000 4

#9250
0!
0(

#9300
1!
b1001010100101 %
1(
b10 ,
b11011110 .
b1001010100101 /
b10 1
b11011110 2
b1001010100101 3

#9350
0!
0(

#9400
1!
b11011111101111 %
1(
b11 ,
b101001101 .
b11011111101111 /
b11 1
b101001101 2
b11011111101111 3

#9450
0!
0(

#9500
1!
b110111111011110 %
1(
b100 ,
b11001 .
b110111111011110 /
b100 1
b11001 2
b110111111011110 3

#9550
0!
0(

#9600
1!
b111010000010001 %
1(
b101 ,
b11010 .
b111010000010001 /
b101 1
b11010 2
b111010000010001 3

#9650
0!
0(

#9700
1!
b111100001101111 %
1(
b110 ,
b11011 .
b111100001101111 /
b110 1
b11011 2
b111100001101111 3

#9750
0!
0(

#9800
1!
b111110011111000 %
1(
b111 ,
b11100 .
b111110011111000 /
b111 1
b11100 2
b111110011111000 3

#9850
0!
0(

#9900
1!
b1000000110101100 %
1(
b0 ,
b11101 .
b1000000110101100 /
b0 1
b11101 2
b1000000110101100 3

#9950
0!
0(

#10000
1!
b1000011010001011 %
1(
b1 ,
b1101111 .
b1000011010001011 /
b1 1
b1101111 2
b1000011010001011 3

#10050
0!
0(

#10100
1!
0#
1(
0*
b1000011010001011 5
b1000011010001011 6

#10150
0!
0(

#10200
1!
1"
b0 %
1(
1)
b0 ,
b0 .
b0 /
b0 1
b0 2
b0 3

#10250
0!
0(

#10300
1!
1(

#10350
0!
0(

#10400
1!
1(

#10450
0!
0(

#10500
1!
1(

#10550
0!
0(

#10600
1!
1(

#10650
0!
0(

#10700
1!
1(

#10750
0!
0(

#10800
1!
1(

#10850
0!
0(

#10900
1!
1(

#10950
0!
0(

#11000
1!
1(

#11050
0!
0(

#11100
1!
1(

#11150
0!
0(

#11200
1!
1(

#11250
0!
0(

#11300
1!
1(

#11350
0!
0(

#11400
1!
1(

#11450
0!
0(

#11500
1!
1(

#11550
0!
0(

#11600
1!
1(

#11650
0!
0(

#11700
1!
1(

#11750
0!
0(

#11800
1!
1(

#11850
0!
0(

#11900
1!
1(

#11950
0!
0(

#12000
1!
1(

#12050
0!
0(

#12100
1!
1(

#12150
0!
0(

#12200
1!
0"
1#
b111111 $
b1100010100011111 '
1(
0)
1*
b111111 +
b1 ,
b1101111 .
b1 1
b1101111 2
b1000 4

#12250
0!
0(

#12300
1!
b1101101010001 %
1(
b10 ,
b11011110 .
b1101101010001 /
b10 1
b11011110 2
b1101101010001 3

#12350
0!
0(

#12400
1!
b101000111110011 %
1(
b11 ,
b101001101 .
b101000111110011 /
b11 1
b101001101 2
b101000111110011 3

#12450
0!
0(

#12500
1!
b1010001111100110 %
1(
b100 ,
b11001 .
b1010001111100110 /
b100 1
b11001 2
b1010001111100110 3

#12550
0!
0(

#12600
1!
b1010101000001101 %
1(
b101 ,
b11010 .
b1010101000001101 /
b101 1
b11010 2
b1010101000001101 3

#12650
0!
0(

#12700
1!
b1011000001110011 %
1(
b110 ,
b11011 .
b1011000001110011 /
b110 1
b11011 2
b1011000001110011 3

#12750
0!
0(

#12800
1!
b1011011100011000 %
1(
b111 ,
b11100 .
b1011011100011000 /
b111 1
b11100 2
b1011011100011000 3

#12850
0!
0(

#12900
1!
b1011110111111100 %
1(
b0 ,
b11101 .
b1011110111111100 /
b0 1
b11101 2
b1011110111111100 3

#12950
0!
0(

#13000
1!
b1100010100011111 %
1(
b1 ,
b1101111 .
b1100010100011111 /
b1 1
b1101111 2
b1100010100011111 3

#13050
0!
0(

#13100
1!
0#
1(
0*
b1100010100011111 5
b1100010100011111 6

#13150
0!
0(

#13200
1!
1"
b0 %
1(
1)
b0 ,
b0 .
b0 /
b0 1
b0 2
b0 3

#13250
0!
0(

#13300
1!
1(

#13350
0!
0(

#13400
1!
1(

#13450
0!
0(

#13500
1!
1(

#13550
0!
0(

#13600
1!
1(

#13650
0!
0(

#13700
1!
1(

#13750
0!
0(

#13800
1!
1(

#13850
0!
0(

#13900
1!
1(

#13950
0!
0(

#14000
1!
1(

#14050
0!
0(

#14100
1!
1(

#14150
0!
0(

#14200
1!
1(

#14250
0!
0(

#14300
1!
1(

#14350
0!
0(

#14400
1!
1(

#14450
0!
0(

#14500
1!
1(

#14550
0!
0(

#14600
1!
1(

#14650
0!
0(

#14700
1!
1(

#14750
0!
0(

#14800
1!
1(

#14850
0!
0(

#14900
1!
1(

#14950
0!
0(

#15000
1!
1(

#15050
0!
0(

#15100
1!
1(

#15150
0!
0(

#15200
1!
0"
1#
b100001 $
b110011101000001 '
1(
0)
1*
b100001 +
b1 ,
b1101111 .
b1 1
b1101111 2
b1000 4

#15250
0!
0(

#15300
1!
b111001001111 %
1(
b10 ,
b11011110 .
b111001001111 /
b10 1
b11011110 2
b111001001111 3

#15350
0!
0(

#15400
1!
b10101011101101 %
1(
b11 ,
b101001101 .
b10101011101101 /
b11 1
b101001101 2
b10101011101101 3

#15450
0!
0(

#15500
1!
b101010111011010 %
1(
b100 ,
b11001 .
b101010111011010 /
b100 1
b11001 2
b101010111011010 3

#15550
0!
0(

#15600
1!
b101100100010011 %
1(
b101 ,
b11010 .
b101100100010011 /
b101 1
b11010 2
b101100100010011 3

#15650
0!
0(

#15700
1!
b101110001101101 %
1(
b110 ,
b11011 .
b101110001101101 /
b110 1
b11011 2
b101110001101101 3

#15750
0!
0(

#15800
1!
b101111111101000 %
1(
b111 ,
b11100 .
b101111111101000 /
b111 1
b11100 2
b101111111101000 3

#15850
0!
0(

#15900
1!
b110001110000100 %
1(
b0 ,
b11101 .
b110001110000100 /
b0 1
b11101 2
b110001110000100 3

#15950
0!
0(

#16000
1!
b110011101000001 %
1(
b1 ,
b1101111 .
b110011101000001 /
b1 1
b1101111 2
b110011101000001 3

#16050
0!
0(

#16100
1!
0#
1(
0*
b110011101000001 5
b110011101000001 6

#16150
0!
0(

#16200
1!
1"
b0 %
1(
1)
b0 ,
b0 .
b0 /
b0 1
b0 2
b0 3

#16250
0!
0(

#16300
1!
1(

#16350
0!
0(

#16400
1!
1(

#16450
0!
0(

#16500
1!
1(

#16550
0!
0(

#16600
1!
1(

#16650
0!
0(

#16700
1!
1(

#16750
0!
0(

#16800
1!
1(

#16850
0!
0(

#16900
1!
1(

#16950
0!
0(

#17000
1!
1(

#17050
0!
0(

#17100
1!
1(

#17150
0!
0(

#17200
1!
1(

#17250
0!
0(

#17300
1!
1(

#17350
0!
0(

#17400
1!
1(

#17450
0!
0(

#17500
1!
1(

#17550
0!
0(

#17600
1!
1(

#17650
0!
0(

#17700
1!
1(

#17750
0!
0(

#17800
1!
1(

#17850
0!
0(

#17900
1!
1(

#17950
0!
0(

#18000
1!
1(

#18050
0!
0(

#18100
1!
1(

#18150
0!
0(

#18200
1!
0"
1#
b111110 $
b1100000111111110 '
1(
0)
1*
b111110 +
b1 ,
b1101111 .
b1 1
b1101111 2
b1000 4

#18250
0!
0(

#18300
1!
b1101011100010 %
1(
b10 ,
b11011110 .
b1101011100010 /
b10 1
b11011110 2
b1101011100010 3

#18350
0!
0(

#18400
1!
b101000010100110 %
1(
b11 ,
b101001101 .
b101000010100110 /
b11 1
b101001101 2
b101000010100110 3

#18450
0!
0(

#18500
1!
b1010000101001100 %
1(
b100 ,
b11001 .
b1010000101001100 /
b100 1
b11001 2
b1010000101001100 3

#18550
0!
0(

#18600
1!
b1010011101011010 %
1(
b101 ,
b11010 .
b1010011101011010 /
b101 1
b11010 2
b1010011101011010 3

#18650
0!
0(

#18700
1!
b1010110110100110 %
1(
b110 ,
b11011 .
b1010110110100110 /
b110 1
b11011 2
b1010110110100110 3

#18750
0!
0(

#18800
1!
b1011010000110000 %
1(
b111 ,
b11100 .
b1011010000110000 /
b111 1
b11100 2
b1011010000110000 3

#18850
0!
0(

#18900
1!
b1011101011111000 %
1(
b0 ,
b11101 .
b1011101011111000 /
b0 1
b11101 2
b1011101011111000 3

#18950
0!
0(

#19000
1!
b1100000111111110 %
1(
b1 ,
b1101111 .
b1100000111111110 /
b1 1
b1101111 2
b1100000111111110 3

#19050
0!
0(

#19100
1!
0#
1(
0*
b1100000111111110 5
b1100000111111110 6

#19150
0!
0(

#19200
1!
1"
b0 %
1(
1)
b0 ,
b0 .
b0 /
b0 1
b0 2
b0 3

#19250
0!
0(

#19300
1!
1(

#19350
0!
0(

#19400
1!
1(

#19450
0!
0(

#19500
1!
1(

#19550
0!
0(

#19600
1!
1(

#19650
0!
0(

#19700
1!
1(

#19750
0!
0(

#19800
1!
1(

#19850
0!
0(

#19900
1!
1(

#19950
0!
0(

#20000
1!
1(

#20050
0!
0(

#20100
1!
1(

#20150
0!
0(

#20200
1!
1(

#20250
0!
0(

#20300
1!
1(

#20350
0!
0(

#20400
1!
1(

#20450
0!
0(

#20500
1!
1(

#20550
0!
0(

#20600
1!
1(

#20650
0!
0(

#20700
1!
1(

#20750
0!
0(

#20800
1!
1(

#20850
0!
0(

#20900
1!
1(

#20950
0!
0(

#21000
1!
1(

#21050
0!
0(

#21100
1!
1(

#21150
0!
0(

#21200
1!
0"
1#
b1111 $
b10111011101111 '
1(
0)
1*
b1111 +
b1 ,
b1101111 .
b1 1
b1101111 2
b1000 4

#21250
0!
0(

#21300
1!
b11010000001 %
1(
b10 ,
b11011110 .
b11010000001 /
b10 1
b11011110 2
b11010000001 3

#21350
0!
0(

#21400
1!
b1001110000011 %
1(
b11 ,
b101001101 .
b1001110000011 /
b11 1
b101001101 2
b1001110000011 3

#21450
0!
0(

#21500
1!
b10011100000110 %
1(
b100 ,
b11001 .
b10011100000110 /
b100 1
b11001 2
b10011100000110 3

#21550
0!
0(

#21600
1!
b10100001111101 %
1(
b101 ,
b11010 .
b10100001111101 /
b101 1
b11010 2
b10100001111101 3

#21650
0!
0(

#21700
1!
b10101000000011 %
1(
b110 ,
b11011 .
b10101000000011 /
b110 1
b11011 2
b10101000000011 3

#21750
0!
0(

#21800
1!
b10101110011000 %
1(
b111 ,
b11100 .
b10101110011000 /
b111 1
b11100 2
b10101110011000 3

#21850
0!
0(

#21900
1!
b10110100111100 %
1(
b0 ,
b11101 .
b10110100111100 /
b0 1
b11101 2
b10110100111100 3

#21950
0!
0(

#22000
1!
b10111011101111 %
1(
b1 ,
b1101111 .
b10111011101111 /
b1 1
b1101111 2
b10111011101111 3

#22050
0!
0(

#22100
1!
0#
1(
0*
b10111011101111 5
b10111011101111 6

#22150
0!
0(

#22200
1!
1"
b0 %
1(
1)
b0 ,
b0 .
b0 /
b0 1
b0 2
b0 3

#22250
0!
0(

#22300
1!
1(

#22350
0!
0(

#22400
1!
1(

#22450
0!
0(

#22500
1!
1(

#22550
0!
0(

#22600
1!
1(

#22650
0!
0(

#22700
1!
1(

#22750
0!
0(

#22800
1!
1(

#22850
0!
0(

#22900
1!
1(

#22950
0!
0(

#23000
1!
1(

#23050
0!
0(

#23100
1!
1(

#23150
0!
0(

#23200
1!
1(

#23250
0!
0(

#23300
1!
1(

#23350
0!
0(

#23400
1!
1(

#23450
0!
0(

#23500
1!
1(

#23550
0!
0(

#23600
1!
1(

#23650
0!
0(

#23700
1!
1(

#23750
0!
0(

#23800
1!
1(

#23850
0!
0(

#23900
1!
1(

#23950
0!
0(

#24000
1!
1(

#24050
0!
0(

#24100
1!
1(

#24150
0!
0(

#24200
1!
0"
1#
b1011 $
b10001001101011 '
1(
0)
1*
b1011 +
b1 ,
b1101111 .
b1 1
b1101111 2
b1000 4

#24250
0!
0(

#24300
1!
b10011000101 %
1(
b10 ,
b11011110 .
b10011000101 /
b10 1
b11011110 2
b10011000101 3

#24350
0!
0(

#24400
1!
b111001001111 %
1(
b11 ,
b101001101 .
b111001001111 /
b11 1
b101001101 2
b111001001111 3

#24450
0!
0(

#24500
1!
b1110010011110 %
1(
b100 ,
b11001 .
b1110010011110 /
b100 1
b11001 2
b1110010011110 3

#24550
0!
0(

#24600
1!
b1110110110001 %
1(
b101 ,
b11010 .
b1110110110001 /
b101 1
b11010 2
b1110110110001 3

#24650
0!
0(

#24700
1!
b1111011001111 %
1(
b110 ,
b11011 .
b1111011001111 /
b110 1
b11011 2
b1111011001111 3

#24750
0!
0(

#24800
1!
b1111111111000 %
1(
b111 ,
b11100 .
b1111111111000 /
b111 1
b11100 2
b1111111111000 3

#24850
0!
0(

#24900
1!
b10000100101100 %
1(
b0 ,
b11101 .
b10000100101100 /
b0 1
b11101 2
b10000100101100 3

#24950
0!
0(

#25000
1!
b10001001101011 %
1(
b1 ,
b1101111 .
b10001001101011 /
b1 1
b1101111 2
b10001001101011 3

#25050
0!
0(

#25100
1!
0#
1(
0*
b10001001101011 5
b10001001101011 6

#25150
0!
0(

#25200
1!
1"
b0 %
1(
1)
b0 ,
b0 .
b0 /
b0 1
b0 2
b0 3

#25250
0!
0(

#25300
1!
1(

#25350
0!
0(

#25400
1!
1(

#25450
0!
0(

#25500
1!
1(

#25550
0!
0(

#25600
1!
1(

#25650
0!
0(

#25700
1!
1(

#25750
0!
0(

#25800
1!
1(

#25850
0!
0(

#25900
1!
1(

#25950
0!
0(

#26000
1!
1(

#26050
0!
0(

#26100
1!
1(

#26150
0!
0(

#26200
1!
1(

#26250
0!
0(

#26300
1!
1(

#26350
0!
0(

#26400
1!
1(

#26450
0!
0(

#26500
1!
1(

#26550
0!
0(

#26600
1!
1(

#26650
0!
0(

#26700
1!
1(

#26750
0!
0(

#26800
1!
1(

#26850
0!
0(

#26900
1!
1(

#26950
0!
0(

#27000
1!
1(

#27050
0!
0(

#27100
1!
1(

#27150
0!
0(

#27200
1!
0"
1#
b100110 $
b111011011100110 '
1(
0)
1*
b100110 +
b1 ,
b1101111 .
b1 1
b1101111 2
b1000 4

#27250
0!
0(

#27300
1!
b1000001111010 %
1(
b10 ,
b11011110 .
b1000001111010 /
b10 1
b11011110 2
b1000001111010 3

#27350
0!
0(

#27400
1!
b11000101101110 %
1(
b11 ,
b101001101 .
b11000101101110 /
b11 1
b101001101 2
b11000101101110 3

#27450
0!
0(

#27500
1!
b110001011011100 %
1(
b100 ,
b11001 .
b110001011011100 /
b100 1
b11001 2
b110001011011100 3

#27550
0!
0(

#27600
1!
b110011010010010 %
1(
b101 ,
b11010 .
b110011010010010 /
b101 1
b11010 2
b110011010010010 3

#27650
0!
0(

#27700
1!
b110101001101110 %
1(
b110 ,
b11011 .
b110101001101110 /
b110 1
b11011 2
b110101001101110 3

#27750
0!
0(

#27800
1!
b110111001110000 %
1(
b111 ,
b11100 .
b110111001110000 /
b111 1
b11100 2
b110111001110000 3

#27850
0!
0(

#27900
1!
b111001010011000 %
1(
b0 ,
b11101 .
b111001010011000 /
b0 1
b11101 2
b111001010011000 3

#27950
0!
0(

#28000
1!
b111011011100110 %
1(
b1 ,
b1101111 .
b111011011100110 /
b1 1
b1101111 2
b111011011100110 3

#28050
0!
0(

#28100
1!
0#
1(
0*
b111011011100110 5
b111011011100110 6

#28150
0!
0(

#28200
1!
1"
b0 %
1(
1)
b0 ,
b0 .
b0 /
b0 1
b0 2
b0 3

#28250
0!
0(

#28300
1!
1(

#28350
0!
0(

#28400
1!
1(

#28450
0!
0(

#28500
1!
1(

#28550
0!
0(

